Workbook
Name HeuresStandardJour: '00_Parametres'!$B$5
Name HeuresStandardMois: '00_Parametres'!$B$7
Name JoursStandardMois: '00_Parametres'!$B$6
Name SeuilHS: '00_Parametres'!$B$9
Name TauxMajorationHS: '00_Parametres'!$B$8

Sheet 00_Dashboard
A1: GARAGE POLYVALENT JUNIOR — TABLEAU DE BORD RH
A2: Mis à jour automatiquement | Fichier professionnel v2.0
A4: INDICATEURS CLÉS
A5: EFFECTIF TOTAL | C5: ACTIFS | E5: CDI | G5: APPRENTISSAGE
A6: =SUMPRODUCT(('01_Employes'!A6:A30<>"")*1) -> 14 | C6: =COUNTIF('01_Employes'!I6:I30,"Actif") -> 14 | E6: =COUNTIF('01_Employes'!K6:K30,"CDI") -> 4 | G6: =COUNTIF('01_Employes'!K6:K30,"Apprentissage") -> 9
A8: MASSE SALARIALE BASE (FCFA) | D8: NBR DÉPARTEMENTS
A9: =SUMIF('01_Employes'!I6:I30,"Actif",'01_Employes'!L6:L30) -> 1440000 | D9: 5
A11: RÉPARTITION PAR POSTE | D11: RÉPARTITION PAR DÉPARTEMENT
A12: Poste | B12: Nombre | D12: Département | E12: Nombre
A13: Administrateur | B13: =COUNTIF('01_Employes'!E$6:E$30,A13) -> 1 | D13: Administration | E13: =COUNTIF('01_Employes'!F$6:F$30,D13) -> 3
A14: Secrétaire | B14: =COUNTIF('01_Employes'!E$6:E$30,A14) -> 1 | D14: Direction Atelier | E14: =COUNTIF('01_Employes'!F$6:F$30,D14) -> 1
A15: Chef des ateliers | B15: =COUNTIF('01_Employes'!E$6:E$30,A15) -> 1 | D15: Atelier Mécanique | E15: =COUNTIF('01_Employes'!F$6:F$30,D15) -> 8
A16: Mécanicien | B16: =COUNTIF('01_Employes'!E$6:E$30,A16) -> 7 | D16: Carrosserie | E16: =COUNTIF('01_Employes'!F$6:F$30,D16) -> 1
A17: Tôlier | B17: =COUNTIF('01_Employes'!E$6:E$30,A17) -> 1 | D17: Magasin | E17: =COUNTIF('01_Employes'!F$6:F$30,D17) -> 1
A18: Magasinier | B18: =COUNTIF('01_Employes'!E$6:E$30,A18) -> 1
A19: Électronicien | B19: =COUNTIF('01_Employes'!E$6:E$30,A19) -> 1
A20: Assistant Administratif | B20: =COUNTIF('01_Employes'!E$6:E$30,A20) -> 1
A23: ACCÈS RAPIDE AUX MODULES
A24: Module | B24: Description
A25: 01_Employes | B25: Fiche complète de chaque employé (identité, contact, poste, contrat, salaire...)
A26: 02_Pointage | B26: Pointage journalier avec heures d'arrivée/départ + primes de tâche
A27: 03_Paie | B27: Calcul automatique du salaire sur heures réelles + primes + HS
A28: 04_Conges | B28: Demandes et suivi des congés / absences + soldes
A29: 05_Contrats | B29: Informations contractuelles et documents
A30: 06_Competences | B30: Compétences, formations et habilitations
A31: 07_Planning | B31: Planning hebdomadaire / affectations
A32: 08_Sanctions | B32: Avertissements, incidents, remarques
A33: 09_Contacts | B33: Annuaire interne prêt à l'emploi
A34: 00_Parametres | B34: Paramètres globaux (heures standard, majoration HS...)

Sheet 00_Parametres
A1: PARAMÈTRES GÉNÉRAUX — GARAGE POLYVALENT JUNIOR
A3: HORAIRES DE TRAVAIL HEBDOMADAIRES (100% MODIFIABLES)
A4: Modifiez librement les jours travaillés (Oui/Non), les heures d'arrivée/départ et la durée de pause. Tous les calculs se mettent à jour automatiquement.
A6: Jour | B6: Travaillé ? (Oui/Non) | C6: Heure Début | D6: Heure Fin | E6: Pause (heures) | F6: Heures nettes / jour | G6: Notes
A7: Lundi | B7: Oui | C7: 0.3125 | D7: 0.75 | E7: 1 | F7: =IF(B7="Oui",IF(OR(C7="",D7=""),0,ROUND((D7-C7)*24-E7,2)),0) -> 9.5 | G7: Jour normal
A8: Mardi | B8: Oui | C8: 0.3125 | D8: 0.75 | E8: 1 | F8: =IF(B8="Oui",IF(OR(C8="",D8=""),0,ROUND((D8-C8)*24-E8,2)),0) -> 9.5 | G8: Jour normal
A9: Mercredi | B9: Oui | C9: 0.3125 | D9: 0.75 | E9: 1 | F9: =IF(B9="Oui",IF(OR(C9="",D9=""),0,ROUND((D9-C9)*24-E9,2)),0) -> 9.5 | G9: Jour normal
A10: Jeudi | B10: Oui | C10: 0.3125 | D10: 0.75 | E10: 1 | F10: =IF(B10="Oui",IF(OR(C10="",D10=""),0,ROUND((D10-C10)*24-E10,2)),0) -> 9.5 | G10: Jour normal
A11: Vendredi | B11: Oui | C11: 0.3125 | D11: 0.75 | E11: 1 | F11: =IF(B11="Oui",IF(OR(C11="",D11=""),0,ROUND((D11-C11)*24-E11,2)),0) -> 9.5 | G11: Jour normal
A12: Samedi | B12: Oui | C12: 0.3125 | D12: 0.5 | E12: 0 | F12: =IF(B12="Oui",IF(OR(C12="",D12=""),0,ROUND((D12-C12)*24-E12,2)),0) -> 4.5 | G12: Matin seulement
A13: Dimanche | B13: Non | E13: 0 | F13: =IF(B13="Oui",IF(OR(C13="",D13=""),0,ROUND((D13-C13)*24-E13,2)),0) -> 0 | G13: Repos
A15: RÉSUMÉ HEBDOMADAIRE (calculé automatiquement)
A16: Jours travaillés / semaine | B16: =COUNTIF(B7:B13,"Oui") -> 6
A17: Heures nettes / semaine | B17: =SUM(F7:F13) -> 52
A18: Heures standard / mois (≈ 4,333 semaines) | B18: =ROUND(B17*4.333,1) -> 225.3 | C18: ← Utilisée pour calculer le taux horaire des employés
A20: PARAMÈTRES GÉNÉRAUX DE CALCUL & RÈGLES DE POINTAGE
A21: Heures standard mensuelles (pour taux horaire) | B21: =B18 -> 225.3
A22: Taux majoration Heures Supp. (ex: 1.5 = +50%) | B22: 1.5
A23: Seuil HS journalier (heures) — au-delà = heures supplémentaires | B23: 9.5
A24: Heures standard d'un jour de semaine (référence) | B24: =F7 -> 9.5
A25: Heures standard d'un samedi (référence) | B25: =F12 -> 4.5
A27: RÈGLES DE COMPTABILISATION DES HEURES (modifiables par l'Admin)
A28: Comptabiliser les arrivées anticipées ? (Oui = extra payé / Non = plafonné à l'heure de début) | B28: Non | C28: Par défaut NON : arriver avant l'heure ne rapporte pas d'heures supplémentaires
A29: Comptabiliser les départs tardifs ? (Oui = extra payé / Non = plafonné à l'heure de fin) | B29: Non | C29: Par défaut NON : rester après l'heure ne rapporte pas d'heures supplémentaires (sauf validation ligne par ligne)
A30: Déduire automatiquement les retards ? | B30: Oui | C30: Absence non justifiée
A31: Déduire automatiquement les départs anticipés ? | B31: Oui | C31: Congé approuvé
A32: M | B32: Maladie | C32: Arrêt maladie
A33: LOGIQUE APPLIQUÉE DANS LE POINTAGE | B33: Retard | C33: Présent avec retard
A34: 1. Arrivée avant l'heure de début → considérée comme arrivée à l'heure (sauf si Admin valide l'anticipation sur la ligne). | B34: Jour Travaillé partiel | C34: Journée partielle
A35: 2. Départ après l'heure de fin → considéré comme départ à l'heure (sauf si Admin valide le départ tardif sur la ligne). | B35: Heures Supplémentaires | C35: Journée avec HS
A36: 3. Arrivée en retard → les minutes de retard sont déduites du temps de travail. | B36: Férié | C36: Jour férié
A37: 4. Départ anticipé → les minutes manquantes sont déduites du temps de travail.
A38: 5. Tous les calculs se font d'abord en minutes, puis conversion en heures décimales (précision maximale).
A39: Postes | B39: Départements | C39: Types de contrat | D39: Statuts | E39: Types d'absence
A40: Administrateur | B40: Administration | C40: CDI | D40: Actif | E40: Congé annuel
A41: Secrétaire | B41: Direction Atelier | C41: CDD | D41: Inactif | E41: Congé maladie
A42: Chef des ateliers | B42: Atelier Mécanique | C42: Apprentissage | D42: Suspendu | E42: Congé maternité
A43: Mécanicien | B43: Carrosserie | C43: Stage | D43: Démissionnaire | E43: Congé sans solde
A44: Tôlier | B44: Magasin | C44: Journalier | D44: Licencié | E44: Absence injustifiée
A45: Magasinier | B45: Direction Générale | C45: Prestataire | E45: Formation
A46: Électronicien | E46: Mission
A47: Assistant Administratif
A48: Apprenti
A49: Autre
A52: INSTRUCTIONS
A53: • JAUNE = saisie (modifiable) | VERT = calculé automatiquement (ne pas toucher)
A54: • Pour changer les jours de travail : mettez Oui ou Non dans la colonne B.
A55: • Pour changer les horaires : modifiez Heure Début, Heure Fin et Pause (en heures décimales).
A56: • Les heures nettes, le total hebdomadaire et le taux horaire des employés se mettent à jour automatiquement.
A57: • Le seuil HS (B23) détermine à partir de combien d'heures dans une journée les heures deviennent supplémentaires.
A58: • Exemple actuel : Lun-Ven 7h30-18h (pause 1h) = 9,5h nettes | Samedi 7h30-12h = 4,5h nettes

Sheet 01_Employes
A1: REGISTRE DU PERSONNEL — GARAGE POLYVALENT JUNIOR
A2: SOURCE DE VÉRITÉ — Toute modification ici se propage automatiquement aux autres feuilles via les formules.
A3: Complétez uniquement les cellules JAUNES. Les colonnes vertes sont calculées automatiquement.
A5: ID | B5: Nom | C5: Prénom | D5: Nom Complet | E5: Poste | F5: Département | G5: Téléphone | H5: Email | I5: Statut | J5: Date d'embauche | K5: Type de contrat | L5: Salaire Base Mensuel (FCFA) | M5: Taux Horaire (FCFA) | N5: Taux HS (FCFA) | O5: N° CNPS | P5: Adresse | Q5: Notes / Observations
A6: EMP001 | B6: Tsafack Ndongmo | C6: Symphonien | D6: =TRIM(B6&" "&C6) -> Tsafack Ndongmo Symphonien | E6: Administrateur | F6: Administration | G6: 677 89 71 62 | I6: Actif | K6: CDI | L6: 150000 | M6: =IF(L6="","",ROUND(L6/'00_Parametres'!$B$21,0)) -> 666 | N6: =IF(M6="","",ROUND(M6*'00_Parametres'!$B$22,0)) -> 999
A7: EMP002 | B7: Pandja Tchatchoua | C7: Syriane | D7: =TRIM(B7&" "&C7) -> Pandja Tchatchoua Syriane | E7: Secrétaire | F7: Administration | G7: 656 04 71 31 | I7: Actif | K7: CDI | L7: 100000 | M7: =IF(L7="","",ROUND(L7/'00_Parametres'!$B$21,0)) -> 444 | N7: =IF(M7="","",ROUND(M7*'00_Parametres'!$B$22,0)) -> 666
A8: EMP003 | B8: Takoueta | C8: Yvan | D8: =TRIM(B8&" "&C8) -> Takoueta Yvan | E8: Chef des ateliers | F8: Direction Atelier | G8: 657 78 99 78 | I8: Actif | K8: CDI | L8: 150000 | M8: =IF(L8="","",ROUND(L8/'00_Parametres'!$B$21,0)) -> 666 | N8: =IF(M8="","",ROUND(M8*'00_Parametres'!$B$22,0)) -> 999
A9: EMP004 | B9: Chekep | C9: Faustin | D9: =TRIM(B9&" "&C9) -> Chekep Faustin | E9: Mécanicien | F9: Atelier Mécanique | G9: 672 67 18 01 | I9: Actif | K9: CDI | L9: 120000 | M9: =IF(L9="","",ROUND(L9/'00_Parametres'!$B$21,0)) -> 533 | N9: =IF(M9="","",ROUND(M9*'00_Parametres'!$B$22,0)) -> 800
A10: EMP005 | B10: Abdou | D10: =TRIM(B10&" "&C10) -> Abdou | E10: Tôlier | F10: Carrosserie | G10: 673 84 48 12 | I10: Actif | K10: Apprentissage | L10: 80000 | M10: =IF(L10="","",ROUND(L10/'00_Parametres'!$B$21,0)) -> 355 | N10: =IF(M10="","",ROUND(M10*'00_Parametres'!$B$22,0)) -> 533
A11: EMP006 | B11: Nyontyen Si | C11: Jean Vinny | D11: =TRIM(B11&" "&C11) -> Nyontyen Si Jean Vinny | E11: Mécanicien | F11: Atelier Mécanique | G11: 694 36 28 38 | I11: Actif | K11: Apprentissage | L11: 80000 | M11: =IF(L11="","",ROUND(L11/'00_Parametres'!$B$21,0)) -> 355 | N11: =IF(M11="","",ROUND(M11*'00_Parametres'!$B$22,0)) -> 533
A12: EMP007 | B12: Holé | C12: Homsala | D12: =TRIM(B12&" "&C12) -> Holé Homsala | E12: Magasinier | F12: Magasin | G12: 699 47 09 80 | H12: holehomsala7@gmail.com | I12: Actif | K12: Apprentissage | L12: 80000 | M12: =IF(L12="","",ROUND(L12/'00_Parametres'!$B$21,0)) -> 355 | N12: =IF(M12="","",ROUND(M12*'00_Parametres'!$B$22,0)) -> 533
A13: EMP008 | B13: Ebene | C13: Ngono | D13: =TRIM(B13&" "&C13) -> Ebene Ngono | E13: Mécanicien | F13: Atelier Mécanique | G13: 653 04 86 11 | I13: Actif | K13: Apprentissage | L13: 80000 | M13: =IF(L13="","",ROUND(L13/'00_Parametres'!$B$21,0)) -> 355 | N13: =IF(M13="","",ROUND(M13*'00_Parametres'!$B$22,0)) -> 533
A14: EMP009 | B14: Tineba | C14: Vital Eric | D14: =TRIM(B14&" "&C14) -> Tineba Vital Eric | E14: Mécanicien | F14: Atelier Mécanique | G14: 698 14 24 06 | I14: Actif | K14: Apprentissage | L14: 80000 | M14: =IF(L14="","",ROUND(L14/'00_Parametres'!$B$21,0)) -> 355 | N14: =IF(M14="","",ROUND(M14*'00_Parametres'!$B$22,0)) -> 533
A15: EMP010 | B15: Deutchoua Tientcheu | C15: Christian | D15: =TRIM(B15&" "&C15) -> Deutchoua Tientcheu Christian | E15: Mécanicien | F15: Atelier Mécanique | G15: 695 07 89 78 / 678 03 61 47 | I15: Actif | K15: Apprentissage | L15: 80000 | M15: =IF(L15="","",ROUND(L15/'00_Parametres'!$B$21,0)) -> 355 | N15: =IF(M15="","",ROUND(M15*'00_Parametres'!$B$22,0)) -> 533
A16: EMP011 | B16: Fouakouet | C16: Youssoufa | D16: =TRIM(B16&" "&C16) -> Fouakouet Youssoufa | E16: Électronicien | F16: Atelier Mécanique | G16: 640 85 90 53 / 620 04 32 29 | I16: Actif | K16: Apprentissage | L16: 80000 | M16: =IF(L16="","",ROUND(L16/'00_Parametres'!$B$21,0)) -> 355 | N16: =IF(M16="","",ROUND(M16*'00_Parametres'!$B$22,0)) -> 533
A17: EMP012 | B17: Ngouamera | C17: Adrien Gildas | D17: =TRIM(B17&" "&C17) -> Ngouamera Adrien Gildas | E17: Mécanicien | F17: Atelier Mécanique | G17: 680 09 48 64 | I17: Actif | K17: Apprentissage | L17: 80000 | M17: =IF(L17="","",ROUND(L17/'00_Parametres'!$B$21,0)) -> 355 | N17: =IF(M17="","",ROUND(M17*'00_Parametres'!$B$22,0)) -> 533
A18: EMP013 | B18: Nague Zemdjui | C18: Arnaud | D18: =TRIM(B18&" "&C18) -> Nague Zemdjui Arnaud | E18: Assistant Administratif | F18: Administration | G18: 658 77 57 44 | H18: arnaudstars@gmail.com | I18: Actif | K18: CDD | L18: 200000 | M18: =IF(L18="","",ROUND(L18/'00_Parametres'!$B$21,0)) -> 888 | N18: =IF(M18="","",ROUND(M18*'00_Parametres'!$B$22,0)) -> 1332
A19: EMP014 | B19: Zo'o Mbarga | C19: Jean Loic | D19: =IF(B19="","",TRIM(B19&" "&C19)) -> Zo'o Mbarga Jean Loic | E19: Mécanicien | F19: Atelier Mécanique | G19: 698 94 92 21 | I19: Actif | J19: 46223 | K19: Apprentissage | L19: 80000 | M19: =IF(L19="","",ROUND(L19/'00_Parametres'!$B$21,0)) -> 355 | N19: =IF(M19="","",ROUND(M19*'00_Parametres'!$B$22,0)) -> 533
D20: =IF(B20="","",TRIM(B20&" "&C20)) | M20: =IF(L20="","",ROUND(L20/'00_Parametres'!$B$21,0)) | N20: =IF(M20="","",ROUND(M20*'00_Parametres'!$B$22,0))
D21: =IF(B21="","",TRIM(B21&" "&C21)) | M21: =IF(L21="","",ROUND(L21/'00_Parametres'!$B$21,0)) | N21: =IF(M21="","",ROUND(M21*'00_Parametres'!$B$22,0))
D22: =IF(B22="","",TRIM(B22&" "&C22)) | M22: =IF(L22="","",ROUND(L22/'00_Parametres'!$B$21,0)) | N22: =IF(M22="","",ROUND(M22*'00_Parametres'!$B$22,0))
D23: =IF(B23="","",TRIM(B23&" "&C23)) | M23: =IF(L23="","",ROUND(L23/'00_Parametres'!$B$21,0)) | N23: =IF(M23="","",ROUND(M23*'00_Parametres'!$B$22,0))
D24: =IF(B24="","",TRIM(B24&" "&C24)) | M24: =IF(L24="","",ROUND(L24/'00_Parametres'!$B$21,0)) | N24: =IF(M24="","",ROUND(M24*'00_Parametres'!$B$22,0))
D25: =IF(B25="","",TRIM(B25&" "&C25)) | M25: =IF(L25="","",ROUND(L25/'00_Parametres'!$B$21,0)) | N25: =IF(M25="","",ROUND(M25*'00_Parametres'!$B$22,0))

Sheet 02_Pointage
A1: POINTAGE GPJ 2026
A2: ASTUCE UX : Pour un même jour, saisissez la Date une fois puis copiez-la vers le bas (Ctrl+D). Ou filtrez par date. Les heures se calculent automatiquement.
A3: Légende : JAUNE = saisie | VERT = calculé auto | ORANGE = validation Admin (Oui pour compter l'extra)
A5: Date | B5: ID Employé | C5: Nom Complet | D5: Jour | E5: H. Début théorique | F5: H. Fin théorique | G5: Pause (h) | H5: Heure Arrivée réelle | I5: Heure Départ réelle | J5: Valider arrivée anticipée ? | K5: Valider départ tardif ? | L5: Arrivée effective | M5: Départ effectif | N5: Minutes de retard | O5: Minutes départ anticipé | P5: Heures travaillées | Q5: Heures Normales | R5: Heures Supp. | S5: Code Présence | T5: Prime Tâche (FCFA) | U5: Notes / Motif
A6: 46258 | B6: EMP001 | C6: =IF(B6="","",IFERROR(VLOOKUP(B6,Employes[[ID]:[Nom Complet]],4,FALSE()),"")) -> Tsafack Ndongmo Symphonien | D6: =IF(A6="","",TEXT(A6,"dddd")) -> dddd | E6: =IF(A6="","",IFERROR(INDEX('00_Parametres'!$C$7:$C$13,WEEKDAY(A6,2)),"")) -> 0.3125 | F6: =IF(A6="","",IFERROR(INDEX('00_Parametres'!$D$7:$D$13,WEEKDAY(A6,2)),"")) -> 0.75 | G6: =IF(A6="","",IFERROR(INDEX('00_Parametres'!$E$7:$E$13,WEEKDAY(A6,2)),0)) -> 1 | H6: 0.30208333 | I6: 0.75694444 | J6: Non | K6: Non | L6: =IF(OR(A6="",H6=""),"",IF(H6<E6,IF(OR(J6="Oui",'00_Parametres'!$B$28="Oui"),H6,E6),H6)) -> 0.3125 | M6: =IF(OR(A6="",I6=""),"",IF(I6>F6,IF(OR(K6="Oui",'00_Parametres'!$B$29="Oui"),I6,F6),I6)) -> 0.75 | N6: =IF(OR(A6="",H6="",E6=""),0,MAX(0,ROUND((H6-E6)*1440,0))) -> 0 | O6: =IF(OR(A6="",I6="",F6=""),0,MAX(0,ROUND((F6-I6)*1440,0))) -> 0 | P6: =IF(OR(L6="",M6=""),0,MAX(0,ROUND((M6-L6)*24-G6,2))) -> 9.5 | Q6: =IF(P6=0,0,MIN(P6,'00_Parametres'!$B$23)) -> 9.5 | R6: =IF(P6=0,0,MAX(0,P6-'00_Parametres'!$B$23)) -> 0 | S6: A | T6: 0 | U6: Arrivé 15 min avant → non compté
A7: 46258 | B7: EMP002 | C7: =IF(B7="","",IFERROR(VLOOKUP(B7,Employes[[ID]:[Nom Complet]],4,FALSE()),"")) -> Pandja Tchatchoua Syriane | D7: =IF(A7="","",TEXT(A7,"dddd")) -> dddd | E7: =IF(A7="","",IFERROR(INDEX('00_Parametres'!$C$7:$C$13,WEEKDAY(A7,2)),"")) -> 0.3125 | F7: =IF(A7="","",IFERROR(INDEX('00_Parametres'!$D$7:$D$13,WEEKDAY(A7,2)),"")) -> 0.75 | G7: =IF(A7="","",IFERROR(INDEX('00_Parametres'!$E$7:$E$13,WEEKDAY(A7,2)),0)) -> 1 | H7: 0.3125 | I7: 0.79166667 | J7: Non | K7: Oui | L7: =IF(OR(A7="",H7=""),"",IF(H7<E7,IF(OR(J7="Oui",'00_Parametres'!$B$28="Oui"),H7,E7),H7)) -> 0.3125 | M7: =IF(OR(A7="",I7=""),"",IF(I7>F7,IF(OR(K7="Oui",'00_Parametres'!$B$29="Oui"),I7,F7),I7)) -> 0.79166667 | N7: =IF(OR(A7="",H7="",E7=""),0,MAX(0,ROUND((H7-E7)*1440,0))) -> 0 | O7: =IF(OR(A7="",I7="",F7=""),0,MAX(0,ROUND((F7-I7)*1440,0))) -> 0 | P7: =IF(OR(L7="",M7=""),0,MAX(0,ROUND((M7-L7)*24-G7,2))) -> 10.5 | Q7: =IF(P7=0,0,MIN(P7,'00_Parametres'!$B$23)) -> 9.5 | R7: =IF(P7=0,0,MAX(0,P7-'00_Parametres'!$B$23)) -> 1 | S7: HS | T7: 5000 | U7: Départ tardif validé Admin
A8: 46258 | B8: EMP003 | C8: =IF(B8="","",IFERROR(VLOOKUP(B8,Employes[[ID]:[Nom Complet]],4,FALSE()),"")) -> Takoueta Yvan | D8: =IF(A8="","",TEXT(A8,"dddd")) -> dddd | E8: =IF(A8="","",IFERROR(INDEX('00_Parametres'!$C$7:$C$13,WEEKDAY(A8,2)),"")) -> 0.3125 | F8: =IF(A8="","",IFERROR(INDEX('00_Parametres'!$D$7:$D$13,WEEKDAY(A8,2)),"")) -> 0.75 | G8: =IF(A8="","",IFERROR(INDEX('00_Parametres'!$E$7:$E$13,WEEKDAY(A8,2)),0)) -> 1 | H8: 0.33333333 | I8: 0.72916667 | J8: Non | K8: Non | L8: =IF(OR(A8="",H8=""),"",IF(H8<E8,IF(OR(J8="Oui",'00_Parametres'!$B$28="Oui"),H8,E8),H8)) -> 0.33333333 | M8: =IF(OR(A8="",I8=""),"",IF(I8>F8,IF(OR(K8="Oui",'00_Parametres'!$B$29="Oui"),I8,F8),I8)) -> 0.72916667 | N8: =IF(OR(A8="",H8="",E8=""),0,MAX(0,ROUND((H8-E8)*1440,0))) -> 30 | O8: =IF(OR(A8="",I8="",F8=""),0,MAX(0,ROUND((F8-I8)*1440,0))) -> 30 | P8: =IF(OR(L8="",M8=""),0,MAX(0,ROUND((M8-L8)*24-G8,2))) -> 8.5 | Q8: =IF(P8=0,0,MIN(P8,'00_Parametres'!$B$23)) -> 8.5 | R8: =IF(P8=0,0,MAX(0,P8-'00_Parametres'!$B$23)) -> 0 | S8: R | T8: 0 | U8: Retard 30 min + départ anticipé 30 min
A9: 46258 | B9: EMP004 | C9: =IF(B9="","",IFERROR(VLOOKUP(B9,Employes[[ID]:[Nom Complet]],4,FALSE()),"")) -> Chekep Faustin | D9: =IF(A9="","",TEXT(A9,"dddd")) -> dddd | E9: =IF(A9="","",IFERROR(INDEX('00_Parametres'!$C$7:$C$13,WEEKDAY(A9,2)),"")) -> 0.3125 | F9: =IF(A9="","",IFERROR(INDEX('00_Parametres'!$D$7:$D$13,WEEKDAY(A9,2)),"")) -> 0.75 | G9: =IF(A9="","",IFERROR(INDEX('00_Parametres'!$E$7:$E$13,WEEKDAY(A9,2)),0)) -> 1 | H9: 0.32291667 | I9: 0.75 | J9: Non | K9: Non | L9: =IF(OR(A9="",H9=""),"",IF(H9<E9,IF(OR(J9="Oui",'00_Parametres'!$B$28="Oui"),H9,E9),H9)) -> 0.32291667 | M9: =IF(OR(A9="",I9=""),"",IF(I9>F9,IF(OR(K9="Oui",'00_Parametres'!$B$29="Oui"),I9,F9),I9)) -> 0.75 | N9: =IF(OR(A9="",H9="",E9=""),0,MAX(0,ROUND((H9-E9)*1440,0))) -> 15 | O9: =IF(OR(A9="",I9="",F9=""),0,MAX(0,ROUND((F9-I9)*1440,0))) -> 0 | P9: =IF(OR(L9="",M9=""),0,MAX(0,ROUND((M9-L9)*24-G9,2))) -> 9.25 | Q9: =IF(P9=0,0,MIN(P9,'00_Parametres'!$B$23)) -> 9.25 | R9: =IF(P9=0,0,MAX(0,P9-'00_Parametres'!$B$23)) -> 0 | S9: R | T9: 0 | U9: Retard 15 min
A10: 46258 | B10: EMP005 | C10: =IF(B10="","",IFERROR(VLOOKUP(B10,Employes[[ID]:[Nom Complet]],4,FALSE()),"")) -> Abdou | D10: =IF(A10="","",TEXT(A10,"dddd")) -> dddd | E10: =IF(A10="","",IFERROR(INDEX('00_Parametres'!$C$7:$C$13,WEEKDAY(A10,2)),"")) -> 0.3125 | F10: =IF(A10="","",IFERROR(INDEX('00_Parametres'!$D$7:$D$13,WEEKDAY(A10,2)),"")) -> 0.75 | G10: =IF(A10="","",IFERROR(INDEX('00_Parametres'!$E$7:$E$13,WEEKDAY(A10,2)),0)) -> 1 | H10: 0.3125 | I10: 0.5 | J10: Non | K10: Non | L10: =IF(OR(A10="",H10=""),"",IF(H10<E10,IF(OR(J10="Oui",'00_Parametres'!$B$28="Oui"),H10,E10),H10)) -> 0.3125 | M10: =IF(OR(A10="",I10=""),"",IF(I10>F10,IF(OR(K10="Oui",'00_Parametres'!$B$29="Oui"),I10,F10),I10)) -> 0.5 | N10: =IF(OR(A10="",H10="",E10=""),0,MAX(0,ROUND((H10-E10)*1440,0))) -> 0 | O10: =IF(OR(A10="",I10="",F10=""),0,MAX(0,ROUND((F10-I10)*1440,0))) -> 360 | P10: =IF(OR(L10="",M10=""),0,MAX(0,ROUND((M10-L10)*24-G10,2))) -> 3.5 | Q10: =IF(P10=0,0,MIN(P10,'00_Parametres'!$B$23)) -> 3.5 | R10: =IF(P10=0,0,MAX(0,P10-'00_Parametres'!$B$23)) -> 0 | S10: P | T10: 2500 | U10: Samedi normal 7h30-12h
A11: 46258 | B11: EMP006 | C11: =IF(B11="","",IFERROR(VLOOKUP(B11,Employes[[ID]:[Nom Complet]],4,FALSE()),"")) -> Nyontyen Si Jean Vinny | D11: =IF(A11="","",TEXT(A11,"dddd")) -> dddd | E11: =IF(A11="","",IFERROR(INDEX('00_Parametres'!$C$7:$C$13,WEEKDAY(A11,2)),"")) -> 0.3125 | F11: =IF(A11="","",IFERROR(INDEX('00_Parametres'!$D$7:$D$13,WEEKDAY(A11,2)),"")) -> 0.75 | G11: =IF(A11="","",IFERROR(INDEX('00_Parametres'!$E$7:$E$13,WEEKDAY(A11,2)),0)) -> 1 | H11: 0.3125 | I11: 0.79166667 | J11: Non | K11: Non | L11: =IF(OR(A11="",H11=""),"",IF(H11<E11,IF(OR(J11="Oui",'00_Parametres'!$B$28="Oui"),H11,E11),H11)) -> 0.3125 | M11: =IF(OR(A11="",I11=""),"",IF(I11>F11,IF(OR(K11="Oui",'00_Parametres'!$B$29="Oui"),I11,F11),I11)) -> 0.75 | N11: =IF(OR(A11="",H11="",E11=""),0,MAX(0,ROUND((H11-E11)*1440,0))) -> 0 | O11: =IF(OR(A11="",I11="",F11=""),0,MAX(0,ROUND((F11-I11)*1440,0))) -> 0 | P11: =IF(OR(L11="",M11=""),0,MAX(0,ROUND((M11-L11)*24-G11,2))) -> 9.5 | Q11: =IF(P11=0,0,MIN(P11,'00_Parametres'!$B$23)) -> 9.5 | R11: =IF(P11=0,0,MAX(0,P11-'00_Parametres'!$B$23)) -> 0
A12: 46258 | B12: EMP007 | C12: =IF(B12="","",IFERROR(VLOOKUP(B12,Employes[[ID]:[Nom Complet]],4,FALSE()),"")) -> Holé Homsala | D12: =IF(A12="","",TEXT(A12,"dddd")) -> dddd | E12: =IF(A12="","",IFERROR(INDEX('00_Parametres'!$C$7:$C$13,WEEKDAY(A12,2)),"")) -> 0.3125 | F12: =IF(A12="","",IFERROR(INDEX('00_Parametres'!$D$7:$D$13,WEEKDAY(A12,2)),"")) -> 0.75 | G12: =IF(A12="","",IFERROR(INDEX('00_Parametres'!$E$7:$E$13,WEEKDAY(A12,2)),0)) -> 1 | H12: 0.625 | I12: 0.70833333 | J12: Non | K12: Non | L12: =IF(OR(A12="",H12=""),"",IF(H12<E12,IF(OR(J12="Oui",'00_Parametres'!$B$28="Oui"),H12,E12),H12)) -> 0.625 | M12: =IF(OR(A12="",I12=""),"",IF(I12>F12,IF(OR(K12="Oui",'00_Parametres'!$B$29="Oui"),I12,F12),I12)) -> 0.70833333 | N12: =IF(OR(A12="",H12="",E12=""),0,MAX(0,ROUND((H12-E12)*1440,0))) -> 450 | O12: =IF(OR(A12="",I12="",F12=""),0,MAX(0,ROUND((F12-I12)*1440,0))) -> 60 | P12: =IF(OR(L12="",M12=""),0,MAX(0,ROUND((M12-L12)*24-G12,2))) -> 1 | Q12: =IF(P12=0,0,MIN(P12,'00_Parametres'!$B$23)) -> 1 | R12: =IF(P12=0,0,MAX(0,P12-'00_Parametres'!$B$23)) -> 0
A13: 46258 | B13: EMP008 | C13: =IF(B13="","",IFERROR(VLOOKUP(B13,Employes[[ID]:[Nom Complet]],4,FALSE()),"")) -> Ebene Ngono | D13: =IF(A13="","",TEXT(A13,"dddd")) -> dddd | E13: =IF(A13="","",IFERROR(INDEX('00_Parametres'!$C$7:$C$13,WEEKDAY(A13,2)),"")) -> 0.3125 | F13: =IF(A13="","",IFERROR(INDEX('00_Parametres'!$D$7:$D$13,WEEKDAY(A13,2)),"")) -> 0.75 | G13: =IF(A13="","",IFERROR(INDEX('00_Parametres'!$E$7:$E$13,WEEKDAY(A13,2)),0)) -> 1 | J13: Non | K13: Non | L13: =IF(OR(A13="",H13=""),"",IF(H13<E13,IF(OR(J13="Oui",'00_Parametres'!$B$28="Oui"),H13,E13),H13)) | M13: =IF(OR(A13="",I13=""),"",IF(I13>F13,IF(OR(K13="Oui",'00_Parametres'!$B$29="Oui"),I13,F13),I13)) | N13: =IF(OR(A13="",H13="",E13=""),0,MAX(0,ROUND((H13-E13)*1440,0))) -> 0 | O13: =IF(OR(A13="",I13="",F13=""),0,MAX(0,ROUND((F13-I13)*1440,0))) -> 0 | P13: =IF(OR(L13="",M13=""),0,MAX(0,ROUND((M13-L13)*24-G13,2))) -> 0 | Q13: =IF(P13=0,0,MIN(P13,'00_Parametres'!$B$23)) -> 0 | R13: =IF(P13=0,0,MAX(0,P13-'00_Parametres'!$B$23)) -> 0
A14: 46258 | B14: EMP009 | C14: =IF(B14="","",IFERROR(VLOOKUP(B14,Employes[[ID]:[Nom Complet]],4,FALSE()),"")) -> Tineba Vital Eric | D14: =IF(A14="","",TEXT(A14,"dddd")) -> dddd | E14: =IF(A14="","",IFERROR(INDEX('00_Parametres'!$C$7:$C$13,WEEKDAY(A14,2)),"")) -> 0.3125 | F14: =IF(A14="","",IFERROR(INDEX('00_Parametres'!$D$7:$D$13,WEEKDAY(A14,2)),"")) -> 0.75 | G14: =IF(A14="","",IFERROR(INDEX('00_Parametres'!$E$7:$E$13,WEEKDAY(A14,2)),0)) -> 1 | J14: Non | K14: Non | L14: =IF(OR(A14="",H14=""),"",IF(H14<E14,IF(OR(J14="Oui",'00_Parametres'!$B$28="Oui"),H14,E14),H14)) | M14: =IF(OR(A14="",I14=""),"",IF(I14>F14,IF(OR(K14="Oui",'00_Parametres'!$B$29="Oui"),I14,F14),I14)) | N14: =IF(OR(A14="",H14="",E14=""),0,MAX(0,ROUND((H14-E14)*1440,0))) -> 0 | O14: =IF(OR(A14="",I14="",F14=""),0,MAX(0,ROUND((F14-I14)*1440,0))) -> 0 | P14: =IF(OR(L14="",M14=""),0,MAX(0,ROUND((M14-L14)*24-G14,2))) -> 0 | Q14: =IF(P14=0,0,MIN(P14,'00_Parametres'!$B$23)) -> 0 | R14: =IF(P14=0,0,MAX(0,P14-'00_Parametres'!$B$23)) -> 0
A15: 46258 | B15: EMP010 | C15: =IF(B15="","",IFERROR(VLOOKUP(B15,Employes[[ID]:[Nom Complet]],4,FALSE()),"")) -> Deutchoua Tientcheu Christian | D15: =IF(A15="","",TEXT(A15,"dddd")) -> dddd | E15: =IF(A15="","",IFERROR(INDEX('00_Parametres'!$C$7:$C$13,WEEKDAY(A15,2)),"")) -> 0.3125 | F15: =IF(A15="","",IFERROR(INDEX('00_Parametres'!$D$7:$D$13,WEEKDAY(A15,2)),"")) -> 0.75 | G15: =IF(A15="","",IFERROR(INDEX('00_Parametres'!$E$7:$E$13,WEEKDAY(A15,2)),0)) -> 1 | J15: Non | K15: Non | L15: =IF(OR(A15="",H15=""),"",IF(H15<E15,IF(OR(J15="Oui",'00_Parametres'!$B$28="Oui"),H15,E15),H15)) | M15: =IF(OR(A15="",I15=""),"",IF(I15>F15,IF(OR(K15="Oui",'00_Parametres'!$B$29="Oui"),I15,F15),I15)) | N15: =IF(OR(A15="",H15="",E15=""),0,MAX(0,ROUND((H15-E15)*1440,0))) -> 0 | O15: =IF(OR(A15="",I15="",F15=""),0,MAX(0,ROUND((F15-I15)*1440,0))) -> 0 | P15: =IF(OR(L15="",M15=""),0,MAX(0,ROUND((M15-L15)*24-G15,2))) -> 0 | Q15: =IF(P15=0,0,MIN(P15,'00_Parametres'!$B$23)) -> 0 | R15: =IF(P15=0,0,MAX(0,P15-'00_Parametres'!$B$23)) -> 0
A16: 46258 | B16: EMP011 | C16: =IF(B16="","",IFERROR(VLOOKUP(B16,Employes[[ID]:[Nom Complet]],4,FALSE()),"")) -> Fouakouet Youssoufa | D16: =IF(A16="","",TEXT(A16,"dddd")) -> dddd | E16: =IF(A16="","",IFERROR(INDEX('00_Parametres'!$C$7:$C$13,WEEKDAY(A16,2)),"")) -> 0.3125 | F16: =IF(A16="","",IFERROR(INDEX('00_Parametres'!$D$7:$D$13,WEEKDAY(A16,2)),"")) -> 0.75 | G16: =IF(A16="","",IFERROR(INDEX('00_Parametres'!$E$7:$E$13,WEEKDAY(A16,2)),0)) -> 1 | J16: Non | K16: Non | L16: =IF(OR(A16="",H16=""),"",IF(H16<E16,IF(OR(J16="Oui",'00_Parametres'!$B$28="Oui"),H16,E16),H16)) | M16: =IF(OR(A16="",I16=""),"",IF(I16>F16,IF(OR(K16="Oui",'00_Parametres'!$B$29="Oui"),I16,F16),I16)) | N16: =IF(OR(A16="",H16="",E16=""),0,MAX(0,ROUND((H16-E16)*1440,0))) -> 0 | O16: =IF(OR(A16="",I16="",F16=""),0,MAX(0,ROUND((F16-I16)*1440,0))) -> 0 | P16: =IF(OR(L16="",M16=""),0,MAX(0,ROUND((M16-L16)*24-G16,2))) -> 0 | Q16: =IF(P16=0,0,MIN(P16,'00_Parametres'!$B$23)) -> 0 | R16: =IF(P16=0,0,MAX(0,P16-'00_Parametres'!$B$23)) -> 0
A17: 46258 | B17: EMP012 | C17: =IF(B17="","",IFERROR(VLOOKUP(B17,Employes[[ID]:[Nom Complet]],4,FALSE()),"")) -> Ngouamera Adrien Gildas | D17: =IF(A17="","",TEXT(A17,"dddd")) -> dddd | E17: =IF(A17="","",IFERROR(INDEX('00_Parametres'!$C$7:$C$13,WEEKDAY(A17,2)),"")) -> 0.3125 | F17: =IF(A17="","",IFERROR(INDEX('00_Parametres'!$D$7:$D$13,WEEKDAY(A17,2)),"")) -> 0.75 | G17: =IF(A17="","",IFERROR(INDEX('00_Parametres'!$E$7:$E$13,WEEKDAY(A17,2)),0)) -> 1 | J17: Non | K17: Non | L17: =IF(OR(A17="",H17=""),"",IF(H17<E17,IF(OR(J17="Oui",'00_Parametres'!$B$28="Oui"),H17,E17),H17)) | M17: =IF(OR(A17="",I17=""),"",IF(I17>F17,IF(OR(K17="Oui",'00_Parametres'!$B$29="Oui"),I17,F17),I17)) | N17: =IF(OR(A17="",H17="",E17=""),0,MAX(0,ROUND((H17-E17)*1440,0))) -> 0 | O17: =IF(OR(A17="",I17="",F17=""),0,MAX(0,ROUND((F17-I17)*1440,0))) -> 0 | P17: =IF(OR(L17="",M17=""),0,MAX(0,ROUND((M17-L17)*24-G17,2))) -> 0 | Q17: =IF(P17=0,0,MIN(P17,'00_Parametres'!$B$23)) -> 0 | R17: =IF(P17=0,0,MAX(0,P17-'00_Parametres'!$B$23)) -> 0
A18: 46258 | B18: EMP013 | C18: =IF(B18="","",IFERROR(VLOOKUP(B18,Employes[[ID]:[Nom Complet]],4,FALSE()),"")) -> Nague Zemdjui Arnaud | D18: =IF(A18="","",TEXT(A18,"dddd")) -> dddd | E18: =IF(A18="","",IFERROR(INDEX('00_Parametres'!$C$7:$C$13,WEEKDAY(A18,2)),"")) -> 0.3125 | F18: =IF(A18="","",IFERROR(INDEX('00_Parametres'!$D$7:$D$13,WEEKDAY(A18,2)),"")) -> 0.75 | G18: =IF(A18="","",IFERROR(INDEX('00_Parametres'!$E$7:$E$13,WEEKDAY(A18,2)),0)) -> 1 | J18: Non | K18: Non | L18: =IF(OR(A18="",H18=""),"",IF(H18<E18,IF(OR(J18="Oui",'00_Parametres'!$B$28="Oui"),H18,E18),H18)) | M18: =IF(OR(A18="",I18=""),"",IF(I18>F18,IF(OR(K18="Oui",'00_Parametres'!$B$29="Oui"),I18,F18),I18)) | N18: =IF(OR(A18="",H18="",E18=""),0,MAX(0,ROUND((H18-E18)*1440,0))) -> 0 | O18: =IF(OR(A18="",I18="",F18=""),0,MAX(0,ROUND((F18-I18)*1440,0))) -> 0 | P18: =IF(OR(L18="",M18=""),0,MAX(0,ROUND((M18-L18)*24-G18,2))) -> 0 | Q18: =IF(P18=0,0,MIN(P18,'00_Parametres'!$B$23)) -> 0 | R18: =IF(P18=0,0,MAX(0,P18-'00_Parametres'!$B$23)) -> 0
C19: =IF(B19="","",IFERROR(VLOOKUP(B19,Employes[[ID]:[Nom Complet]],4,FALSE()),"")) | D19: =IF(A19="","",TEXT(A19,"dddd")) | E19: =IF(A19="","",IFERROR(INDEX('00_Parametres'!$C$7:$C$13,WEEKDAY(A19,2)),"")) | F19: =IF(A19="","",IFERROR(INDEX('00_Parametres'!$D$7:$D$13,WEEKDAY(A19,2)),"")) | G19: =IF(A19="","",IFERROR(INDEX('00_Parametres'!$E$7:$E$13,WEEKDAY(A19,2)),0)) | J19: Non | K19: Non | L19: =IF(OR(A19="",H19=""),"",IF(H19<E19,IF(OR(J19="Oui",'00_Parametres'!$B$28="Oui"),H19,E19),H19)) | M19: =IF(OR(A19="",I19=""),"",IF(I19>F19,IF(OR(K19="Oui",'00_Parametres'!$B$29="Oui"),I19,F19),I19)) | N19: =IF(OR(A19="",H19="",E19=""),0,MAX(0,ROUND((H19-E19)*1440,0))) -> 0 | O19: =IF(OR(A19="",I19="",F19=""),0,MAX(0,ROUND((F19-I19)*1440,0))) -> 0 | P19: =IF(OR(L19="",M19=""),0,MAX(0,ROUND((M19-L19)*24-G19,2))) -> 0 | Q19: =IF(P19=0,0,MIN(P19,'00_Parametres'!$B$23)) -> 0 | R19: =IF(P19=0,0,MAX(0,P19-'00_Parametres'!$B$23)) -> 0
A20: 46259 | B20: EMP001 | C20: =IF(B20="","",IFERROR(VLOOKUP(B20,Employes[[ID]:[Nom Complet]],4,FALSE()),"")) -> Tsafack Ndongmo Symphonien | D20: =IF(A20="","",TEXT(A20,"dddd")) -> dddd | E20: =IF(A20="","",IFERROR(INDEX('00_Parametres'!$C$7:$C$13,WEEKDAY(A20,2)),"")) -> 0.3125 | F20: =IF(A20="","",IFERROR(INDEX('00_Parametres'!$D$7:$D$13,WEEKDAY(A20,2)),"")) -> 0.75 | G20: =IF(A20="","",IFERROR(INDEX('00_Parametres'!$E$7:$E$13,WEEKDAY(A20,2)),0)) -> 1 | H20: 0.40277778 | I20: 0.83333333 | J20: Non | K20: Non | L20: =IF(OR(A20="",H20=""),"",IF(H20<E20,IF(OR(J20="Oui",'00_Parametres'!$B$28="Oui"),H20,E20),H20)) -> 0.40277778 | M20: =IF(OR(A20="",I20=""),"",IF(I20>F20,IF(OR(K20="Oui",'00_Parametres'!$B$29="Oui"),I20,F20),I20)) -> 0.75 | N20: =IF(OR(A20="",H20="",E20=""),0,MAX(0,ROUND((H20-E20)*1440,0))) -> 130 | O20: =IF(OR(A20="",I20="",F20=""),0,MAX(0,ROUND((F20-I20)*1440,0))) -> 0 | P20: =IF(OR(L20="",M20=""),0,MAX(0,ROUND((M20-L20)*24-G20,2))) -> 7.33 | Q20: =IF(P20=0,0,MIN(P20,'00_Parametres'!$B$23)) -> 7.33 | R20: =IF(P20=0,0,MAX(0,P20-'00_Parametres'!$B$23)) -> 0
A21: 46259 | B21: EMP002 | C21: =IF(B21="","",IFERROR(VLOOKUP(B21,Employes[[ID]:[Nom Complet]],4,FALSE()),"")) -> Pandja Tchatchoua Syriane | D21: =IF(A21="","",TEXT(A21,"dddd")) -> dddd | E21: =IF(A21="","",IFERROR(INDEX('00_Parametres'!$C$7:$C$13,WEEKDAY(A21,2)),"")) -> 0.3125 | F21: =IF(A21="","",IFERROR(INDEX('00_Parametres'!$D$7:$D$13,WEEKDAY(A21,2)),"")) -> 0.75 | G21: =IF(A21="","",IFERROR(INDEX('00_Parametres'!$E$7:$E$13,WEEKDAY(A21,2)),0)) -> 1 | H21: 0.47916667 | I21: 0.75 | J21: Non | K21: Non | L21: =IF(OR(A21="",H21=""),"",IF(H21<E21,IF(OR(J21="Oui",'00_Parametres'!$B$28="Oui"),H21,E21),H21)) -> 0.47916667 | M21: =IF(OR(A21="",I21=""),"",IF(I21>F21,IF(OR(K21="Oui",'00_Parametres'!$B$29="Oui"),I21,F21),I21)) -> 0.75 | N21: =IF(OR(A21="",H21="",E21=""),0,MAX(0,ROUND((H21-E21)*1440,0))) -> 240 | O21: =IF(OR(A21="",I21="",F21=""),0,MAX(0,ROUND((F21-I21)*1440,0))) -> 0 | P21: =IF(OR(L21="",M21=""),0,MAX(0,ROUND((M21-L21)*24-G21,2))) -> 5.5 | Q21: =IF(P21=0,0,MIN(P21,'00_Parametres'!$B$23)) -> 5.5 | R21: =IF(P21=0,0,MAX(0,P21-'00_Parametres'!$B$23)) -> 0
A22: 46259 | B22: EMP003 | C22: =IF(B22="","",IFERROR(VLOOKUP(B22,Employes[[ID]:[Nom Complet]],4,FALSE()),"")) -> Takoueta Yvan | D22: =IF(A22="","",TEXT(A22,"dddd")) -> dddd | E22: =IF(A22="","",IFERROR(INDEX('00_Parametres'!$C$7:$C$13,WEEKDAY(A22,2)),"")) -> 0.3125 | F22: =IF(A22="","",IFERROR(INDEX('00_Parametres'!$D$7:$D$13,WEEKDAY(A22,2)),"")) -> 0.75 | G22: =IF(A22="","",IFERROR(INDEX('00_Parametres'!$E$7:$E$13,WEEKDAY(A22,2)),0)) -> 1 | H22: 0.375 | I22: 0.85416667 | J22: Non | K22: Non | L22: =IF(OR(A22="",H22=""),"",IF(H22<E22,IF(OR(J22="Oui",'00_Parametres'!$B$28="Oui"),H22,E22),H22)) -> 0.375 | M22: =IF(OR(A22="",I22=""),"",IF(I22>F22,IF(OR(K22="Oui",'00_Parametres'!$B$29="Oui"),I22,F22),I22)) -> 0.75 | N22: =IF(OR(A22="",H22="",E22=""),0,MAX(0,ROUND((H22-E22)*1440,0))) -> 90 | O22: =IF(OR(A22="",I22="",F22=""),0,MAX(0,ROUND((F22-I22)*1440,0))) -> 0 | P22: =IF(OR(L22="",M22=""),0,MAX(0,ROUND((M22-L22)*24-G22,2))) -> 8 | Q22: =IF(P22=0,0,MIN(P22,'00_Parametres'!$B$23)) -> 8 | R22: =IF(P22=0,0,MAX(0,P22-'00_Parametres'!$B$23)) -> 0
A23: 46259 | B23: EMP004 | C23: =IF(B23="","",IFERROR(VLOOKUP(B23,Employes[[ID]:[Nom Complet]],4,FALSE()),"")) -> Chekep Faustin | D23: =IF(A23="","",TEXT(A23,"dddd")) -> dddd | E23: =IF(A23="","",IFERROR(INDEX('00_Parametres'!$C$7:$C$13,WEEKDAY(A23,2)),"")) -> 0.3125 | F23: =IF(A23="","",IFERROR(INDEX('00_Parametres'!$D$7:$D$13,WEEKDAY(A23,2)),"")) -> 0.75 | G23: =IF(A23="","",IFERROR(INDEX('00_Parametres'!$E$7:$E$13,WEEKDAY(A23,2)),0)) -> 1 | H23: 0.33541667 | I23: 0.79166667 | J23: Non | K23: Non | L23: =IF(OR(A23="",H23=""),"",IF(H23<E23,IF(OR(J23="Oui",'00_Parametres'!$B$28="Oui"),H23,E23),H23)) -> 0.33541667 | M23: =IF(OR(A23="",I23=""),"",IF(I23>F23,IF(OR(K23="Oui",'00_Parametres'!$B$29="Oui"),I23,F23),I23)) -> 0.75 | N23: =IF(OR(A23="",H23="",E23=""),0,MAX(0,ROUND((H23-E23)*1440,0))) -> 33 | O23: =IF(OR(A23="",I23="",F23=""),0,MAX(0,ROUND((F23-I23)*1440,0))) -> 0 | P23: =IF(OR(L23="",M23=""),0,MAX(0,ROUND((M23-L23)*24-G23,2))) -> 8.95 | Q23: =IF(P23=0,0,MIN(P23,'00_Parametres'!$B$23)) -> 8.95 | R23: =IF(P23=0,0,MAX(0,P23-'00_Parametres'!$B$23)) -> 0
A24: 46259 | B24: EMP005 | C24: =IF(B24="","",IFERROR(VLOOKUP(B24,Employes[[ID]:[Nom Complet]],4,FALSE()),"")) -> Abdou | D24: =IF(A24="","",TEXT(A24,"dddd")) -> dddd | E24: =IF(A24="","",IFERROR(INDEX('00_Parametres'!$C$7:$C$13,WEEKDAY(A24,2)),"")) -> 0.3125 | F24: =IF(A24="","",IFERROR(INDEX('00_Parametres'!$D$7:$D$13,WEEKDAY(A24,2)),"")) -> 0.75 | G24: =IF(A24="","",IFERROR(INDEX('00_Parametres'!$E$7:$E$13,WEEKDAY(A24,2)),0)) -> 1 | H24: 0.33333333 | I24: 0.79166667 | J24: Non | K24: Non | L24: =IF(OR(A24="",H24=""),"",IF(H24<E24,IF(OR(J24="Oui",'00_Parametres'!$B$28="Oui"),H24,E24),H24)) -> 0.33333333 | M24: =IF(OR(A24="",I24=""),"",IF(I24>F24,IF(OR(K24="Oui",'00_Parametres'!$B$29="Oui"),I24,F24),I24)) -> 0.75 | N24: =IF(OR(A24="",H24="",E24=""),0,MAX(0,ROUND((H24-E24)*1440,0))) -> 30 | O24: =IF(OR(A24="",I24="",F24=""),0,MAX(0,ROUND((F24-I24)*1440,0))) -> 0 | P24: =IF(OR(L24="",M24=""),0,MAX(0,ROUND((M24-L24)*24-G24,2))) -> 9 | Q24: =IF(P24=0,0,MIN(P24,'00_Parametres'!$B$23)) -> 9 | R24: =IF(P24=0,0,MAX(0,P24-'00_Parametres'!$B$23)) -> 0
A25: 46259 | B25: EMP006 | C25: =IF(B25="","",IFERROR(VLOOKUP(B25,Employes[[ID]:[Nom Complet]],4,FALSE()),"")) -> Nyontyen Si Jean Vinny | D25: =IF(A25="","",TEXT(A25,"dddd")) -> dddd | E25: =IF(A25="","",IFERROR(INDEX('00_Parametres'!$C$7:$C$13,WEEKDAY(A25,2)),"")) -> 0.3125 | F25: =IF(A25="","",IFERROR(INDEX('00_Parametres'!$D$7:$D$13,WEEKDAY(A25,2)),"")) -> 0.75 | G25: =IF(A25="","",IFERROR(INDEX('00_Parametres'!$E$7:$E$13,WEEKDAY(A25,2)),0)) -> 1 | H25: 0.34791667 | I25: 0.75 | J25: Non | K25: Non | L25: =IF(OR(A25="",H25=""),"",IF(H25<E25,IF(OR(J25="Oui",'00_Parametres'!$B$28="Oui"),H25,E25),H25)) -> 0.34791667 | M25: =IF(OR(A25="",I25=""),"",IF(I25>F25,IF(OR(K25="Oui",'00_Parametres'!$B$29="Oui"),I25,F25),I25)) -> 0.75 | N25: =IF(OR(A25="",H25="",E25=""),0,MAX(0,ROUND((H25-E25)*1440,0))) -> 51 | O25: =IF(OR(A25="",I25="",F25=""),0,MAX(0,ROUND((F25-I25)*1440,0))) -> 0 | P25: =IF(OR(L25="",M25=""),0,MAX(0,ROUND((M25-L25)*24-G25,2))) -> 8.65 | Q25: =IF(P25=0,0,MIN(P25,'00_Parametres'!$B$23)) -> 8.65 | R25: =IF(P25=0,0,MAX(0,P25-'00_Parametres'!$B$23)) -> 0
A26: 46259 | B26: EMP007 | C26: =IF(B26="","",IFERROR(VLOOKUP(B26,Employes[[ID]:[Nom Complet]],4,FALSE()),"")) -> Holé Homsala | D26: =IF(A26="","",TEXT(A26,"dddd")) -> dddd | E26: =IF(A26="","",IFERROR(INDEX('00_Parametres'!$C$7:$C$13,WEEKDAY(A26,2)),"")) -> 0.3125 | F26: =IF(A26="","",IFERROR(INDEX('00_Parametres'!$D$7:$D$13,WEEKDAY(A26,2)),"")) -> 0.75 | G26: =IF(A26="","",IFERROR(INDEX('00_Parametres'!$E$7:$E$13,WEEKDAY(A26,2)),0)) -> 1 | H26: 0.35694444 | I26: 0.79166667 | J26: Non | K26: Non | L26: =IF(OR(A26="",H26=""),"",IF(H26<E26,IF(OR(J26="Oui",'00_Parametres'!$B$28="Oui"),H26,E26),H26)) -> 0.35694444 | M26: =IF(OR(A26="",I26=""),"",IF(I26>F26,IF(OR(K26="Oui",'00_Parametres'!$B$29="Oui"),I26,F26),I26)) -> 0.75 | N26: =IF(OR(A26="",H26="",E26=""),0,MAX(0,ROUND((H26-E26)*1440,0))) -> 64 | O26: =IF(OR(A26="",I26="",F26=""),0,MAX(0,ROUND((F26-I26)*1440,0))) -> 0 | P26: =IF(OR(L26="",M26=""),0,MAX(0,ROUND((M26-L26)*24-G26,2))) -> 8.43 | Q26: =IF(P26=0,0,MIN(P26,'00_Parametres'!$B$23)) -> 8.43 | R26: =IF(P26=0,0,MAX(0,P26-'00_Parametres'!$B$23)) -> 0
A27: 46259 | B27: EMP008 | C27: =IF(B27="","",IFERROR(VLOOKUP(B27,Employes[[ID]:[Nom Complet]],4,FALSE()),"")) -> Ebene Ngono | D27: =IF(A27="","",TEXT(A27,"dddd")) -> dddd | E27: =IF(A27="","",IFERROR(INDEX('00_Parametres'!$C$7:$C$13,WEEKDAY(A27,2)),"")) -> 0.3125 | F27: =IF(A27="","",IFERROR(INDEX('00_Parametres'!$D$7:$D$13,WEEKDAY(A27,2)),"")) -> 0.75 | G27: =IF(A27="","",IFERROR(INDEX('00_Parametres'!$E$7:$E$13,WEEKDAY(A27,2)),0)) -> 1 | H27: 0.31944444 | I27: 0.79166667 | J27: Non | K27: Non | L27: =IF(OR(A27="",H27=""),"",IF(H27<E27,IF(OR(J27="Oui",'00_Parametres'!$B$28="Oui"),H27,E27),H27)) -> 0.31944444 | M27: =IF(OR(A27="",I27=""),"",IF(I27>F27,IF(OR(K27="Oui",'00_Parametres'!$B$29="Oui"),I27,F27),I27)) -> 0.75 | N27: =IF(OR(A27="",H27="",E27=""),0,MAX(0,ROUND((H27-E27)*1440,0))) -> 10 | O27: =IF(OR(A27="",I27="",F27=""),0,MAX(0,ROUND((F27-I27)*1440,0))) -> 0 | P27: =IF(OR(L27="",M27=""),0,MAX(0,ROUND((M27-L27)*24-G27,2))) -> 9.33 | Q27: =IF(P27=0,0,MIN(P27,'00_Parametres'!$B$23)) -> 9.33 | R27: =IF(P27=0,0,MAX(0,P27-'00_Parametres'!$B$23)) -> 0
A28: 46259 | B28: EMP009 | C28: =IF(B28="","",IFERROR(VLOOKUP(B28,Employes[[ID]:[Nom Complet]],4,FALSE()),"")) -> Tineba Vital Eric | D28: =IF(A28="","",TEXT(A28,"dddd")) -> dddd | E28: =IF(A28="","",IFERROR(INDEX('00_Parametres'!$C$7:$C$13,WEEKDAY(A28,2)),"")) -> 0.3125 | F28: =IF(A28="","",IFERROR(INDEX('00_Parametres'!$D$7:$D$13,WEEKDAY(A28,2)),"")) -> 0.75 | G28: =IF(A28="","",IFERROR(INDEX('00_Parametres'!$E$7:$E$13,WEEKDAY(A28,2)),0)) -> 1 | H28: 0.34375 | I28: 0.79166667 | J28: Non | K28: Non | L28: =IF(OR(A28="",H28=""),"",IF(H28<E28,IF(OR(J28="Oui",'00_Parametres'!$B$28="Oui"),H28,E28),H28)) -> 0.34375 | M28: =IF(OR(A28="",I28=""),"",IF(I28>F28,IF(OR(K28="Oui",'00_Parametres'!$B$29="Oui"),I28,F28),I28)) -> 0.75 | N28: =IF(OR(A28="",H28="",E28=""),0,MAX(0,ROUND((H28-E28)*1440,0))) -> 45 | O28: =IF(OR(A28="",I28="",F28=""),0,MAX(0,ROUND((F28-I28)*1440,0))) -> 0 | P28: =IF(OR(L28="",M28=""),0,MAX(0,ROUND((M28-L28)*24-G28,2))) -> 8.75 | Q28: =IF(P28=0,0,MIN(P28,'00_Parametres'!$B$23)) -> 8.75 | R28: =IF(P28=0,0,MAX(0,P28-'00_Parametres'!$B$23)) -> 0
A29: 46259 | B29: EMP010 | C29: =IF(B29="","",IFERROR(VLOOKUP(B29,Employes[[ID]:[Nom Complet]],4,FALSE()),"")) -> Deutchoua Tientcheu Christian | D29: =IF(A29="","",TEXT(A29,"dddd")) -> dddd | E29: =IF(A29="","",IFERROR(INDEX('00_Parametres'!$C$7:$C$13,WEEKDAY(A29,2)),"")) -> 0.3125 | F29: =IF(A29="","",IFERROR(INDEX('00_Parametres'!$D$7:$D$13,WEEKDAY(A29,2)),"")) -> 0.75 | G29: =IF(A29="","",IFERROR(INDEX('00_Parametres'!$E$7:$E$13,WEEKDAY(A29,2)),0)) -> 1 | H29: 0.5 | I29: 0.8125 | J29: Non | K29: Non | L29: =IF(OR(A29="",H29=""),"",IF(H29<E29,IF(OR(J29="Oui",'00_Parametres'!$B$28="Oui"),H29,E29),H29)) -> 0.5 | M29: =IF(OR(A29="",I29=""),"",IF(I29>F29,IF(OR(K29="Oui",'00_Parametres'!$B$29="Oui"),I29,F29),I29)) -> 0.75 | N29: =IF(OR(A29="",H29="",E29=""),0,MAX(0,ROUND((H29-E29)*1440,0))) -> 270 | O29: =IF(OR(A29="",I29="",F29=""),0,MAX(0,ROUND((F29-I29)*1440,0))) -> 0 | P29: =IF(OR(L29="",M29=""),0,MAX(0,ROUND((M29-L29)*24-G29,2))) -> 5 | Q29: =IF(P29=0,0,MIN(P29,'00_Parametres'!$B$23)) -> 5 | R29: =IF(P29=0,0,MAX(0,P29-'00_Parametres'!$B$23)) -> 0
A30: 46259 | B30: EMP011 | C30: =IF(B30="","",IFERROR(VLOOKUP(B30,Employes[[ID]:[Nom Complet]],4,FALSE()),"")) -> Fouakouet Youssoufa | D30: =IF(A30="","",TEXT(A30,"dddd")) -> dddd | E30: =IF(A30="","",IFERROR(INDEX('00_Parametres'!$C$7:$C$13,WEEKDAY(A30,2)),"")) -> 0.3125 | F30: =IF(A30="","",IFERROR(INDEX('00_Parametres'!$D$7:$D$13,WEEKDAY(A30,2)),"")) -> 0.75 | G30: =IF(A30="","",IFERROR(INDEX('00_Parametres'!$E$7:$E$13,WEEKDAY(A30,2)),0)) -> 1 | H30: 0.41666667 | I30: 0.75 | J30: Non | K30: Non | L30: =IF(OR(A30="",H30=""),"",IF(H30<E30,IF(OR(J30="Oui",'00_Parametres'!$B$28="Oui"),H30,E30),H30)) -> 0.41666667 | M30: =IF(OR(A30="",I30=""),"",IF(I30>F30,IF(OR(K30="Oui",'00_Parametres'!$B$29="Oui"),I30,F30),I30)) -> 0.75 | N30: =IF(OR(A30="",H30="",E30=""),0,MAX(0,ROUND((H30-E30)*1440,0))) -> 150 | O30: =IF(OR(A30="",I30="",F30=""),0,MAX(0,ROUND((F30-I30)*1440,0))) -> 0 | P30: =IF(OR(L30="",M30=""),0,MAX(0,ROUND((M30-L30)*24-G30,2))) -> 7 | Q30: =IF(P30=0,0,MIN(P30,'00_Parametres'!$B$23)) -> 7 | R30: =IF(P30=0,0,MAX(0,P30-'00_Parametres'!$B$23)) -> 0
A31: 46259 | B31: EMP012 | C31: =IF(B31="","",IFERROR(VLOOKUP(B31,Employes[[ID]:[Nom Complet]],4,FALSE()),"")) -> Ngouamera Adrien Gildas | D31: =IF(A31="","",TEXT(A31,"dddd")) -> dddd | E31: =IF(A31="","",IFERROR(INDEX('00_Parametres'!$C$7:$C$13,WEEKDAY(A31,2)),"")) -> 0.3125 | F31: =IF(A31="","",IFERROR(INDEX('00_Parametres'!$D$7:$D$13,WEEKDAY(A31,2)),"")) -> 0.75 | G31: =IF(A31="","",IFERROR(INDEX('00_Parametres'!$E$7:$E$13,WEEKDAY(A31,2)),0)) -> 1 | H31: 0.33611111 | I31: 0.79166667 | J31: Non | K31: Non | L31: =IF(OR(A31="",H31=""),"",IF(H31<E31,IF(OR(J31="Oui",'00_Parametres'!$B$28="Oui"),H31,E31),H31)) -> 0.33611111 | M31: =IF(OR(A31="",I31=""),"",IF(I31>F31,IF(OR(K31="Oui",'00_Parametres'!$B$29="Oui"),I31,F31),I31)) -> 0.75 | N31: =IF(OR(A31="",H31="",E31=""),0,MAX(0,ROUND((H31-E31)*1440,0))) -> 34 | O31: =IF(OR(A31="",I31="",F31=""),0,MAX(0,ROUND((F31-I31)*1440,0))) -> 0 | P31: =IF(OR(L31="",M31=""),0,MAX(0,ROUND((M31-L31)*24-G31,2))) -> 8.93 | Q31: =IF(P31=0,0,MIN(P31,'00_Parametres'!$B$23)) -> 8.93 | R31: =IF(P31=0,0,MAX(0,P31-'00_Parametres'!$B$23)) -> 0
... A33: 46259 | B33: EMP014 | C33: =IF(B33="","",IFERROR(VLOOKUP(B33,Employes[[ID]:[Nom Complet]],4,FALSE()),"")) -> Zo'o Mbarga Jean Loic | D33: =IF(A33="","",TEXT(A33,"dddd")) -> dddd | E33: =IF(A33="","",IFERROR(INDEX('00_Parametres'!$C$7:$C$13,WEEKDAY(A33,2)),"")) -> 0.3125 | F33: =IF(A33="","",IFERROR(INDEX('00_Parametres'!$D$7:$D$13,WEEKDAY(A33,2)),"")) -> 0.75 | G33: =IF(A33="","",IFERROR(INDEX('00_Parametres'!$E$7:$E$13,WEEKDAY(A33,2)),0)) -> 1 | H33: 0.33333333 | I33: 0.75 | J33: Non | K33: Non | L33: =IF(OR(A33="",H33=""),"",IF(H33<E33,IF(OR(J33="Oui",'00_Parametres'!$B$28="Oui"),H33,E33),H33)) -> 0.33333333 | M33: =IF(OR(A33="",I33=""),"",IF(I33>F33,IF(OR(K33="Oui",'00_Parametres'!$B$29="Oui"),I33,F33),I33)) -> 0.75 | N33: =IF(OR(A33="",H33="",E33=""),0,MAX(0,ROUND((H33-E33)*1440,0))) -> 30 | O33: =IF(OR(A33="",I33="",F33=""),0,MAX(0,ROUND((F33-I33)*1440,0))) -> 0 | P33: =IF(OR(L33="",M33=""),0,MAX(0,ROUND((M33-L33)*24-G33,2))) -> 9 | Q33: =IF(P33=0,0,MIN(P33,'00_Parametres'!$B$23)) -> 9 | R33: =IF(P33=0,0,MAX(0,P33-'00_Parametres'!$B$23)) -> 0
C34: =IF(B34="","",IFERROR(VLOOKUP(B34,Employes[[ID]:[Nom Complet]],4,FALSE()),"")) | D34: =IF(A34="","",TEXT(A34,"dddd")) | E34: =IF(A34="","",IFERROR(INDEX('00_Parametres'!$C$7:$C$13,WEEKDAY(A34,2)),"")) | F34: =IF(A34="","",IFERROR(INDEX('00_Parametres'!$D$7:$D$13,WEEKDAY(A34,2)),"")) | G34: =IF(A34="","",IFERROR(INDEX('00_Parametres'!$E$7:$E$13,WEEKDAY(A34,2)),0)) | J34: Non | K34: Non | L34: =IF(OR(A34="",H34=""),"",IF(H34<E34,IF(OR(J34="Oui",'00_Parametres'!$B$28="Oui"),H34,E34),H34)) | M34: =IF(OR(A34="",I34=""),"",IF(I34>F34,IF(OR(K34="Oui",'00_Parametres'!$B$29="Oui"),I34,F34),I34)) | N34: =IF(OR(A34="",H34="",E34=""),0,MAX(0,ROUND((H34-E34)*1440,0))) -> 0 | O34: =IF(OR(A34="",I34="",F34=""),0,MAX(0,ROUND((F34-I34)*1440,0))) -> 0 | P34: =IF(OR(L34="",M34=""),0,MAX(0,ROUND((M34-L34)*24-G34,2))) -> 0 | Q34: =IF(P34=0,0,MIN(P34,'00_Parametres'!$B$23)) -> 0 | R34: =IF(P34=0,0,MAX(0,P34-'00_Parametres'!$B$23)) -> 0
A35: 46260 | B35: EMP001 | C35: =IF(B35="","",IFERROR(VLOOKUP(B35,Employes[[ID]:[Nom Complet]],4,FALSE()),"")) -> Tsafack Ndongmo Symphonien | D35: =IF(A35="","",TEXT(A35,"dddd")) -> 8/262026 | E35: =IF(A35="","",IFERROR(INDEX('00_Parametres'!$C$7:$C$13,WEEKDAY(A35,2)),"")) | F35: =IF(A35="","",IFERROR(INDEX('00_Parametres'!$D$7:$D$13,WEEKDAY(A35,2)),"")) | G35: =IF(A35="","",IFERROR(INDEX('00_Parametres'!$E$7:$E$13,WEEKDAY(A35,2)),0)) -> 0 | H35: 0.3125 | J35: Non | K35: Non | L35: =IF(OR(A35="",H35=""),"",IF(H35<E35,IF(OR(J35="Oui",'00_Parametres'!$B$28="Oui"),H35,E35),H35)) | M35: =IF(OR(A35="",I35=""),"",IF(I35>F35,IF(OR(K35="Oui",'00_Parametres'!$B$29="Oui"),I35,F35),I35)) | N35: =IF(OR(A35="",H35="",E35=""),0,MAX(0,ROUND((H35-E35)*1440,0))) -> 0 | O35: =IF(OR(A35="",I35="",F35=""),0,MAX(0,ROUND((F35-I35)*1440,0))) -> 0 | P35: =IF(OR(L35="",M35=""),0,MAX(0,ROUND((M35-L35)*24-G35,2))) -> 0 | Q35: =IF(P35=0,0,MIN(P35,'00_Parametres'!$B$23)) -> 0 | R35: =IF(P35=0,0,MAX(0,P35-'00_Parametres'!$B$23)) -> 0
A36: 46260 | B36: EMP002 | C36: =IF(B36="","",IFERROR(VLOOKUP(B36,Employes[[ID]:[Nom Complet]],4,FALSE()),"")) -> Pandja Tchatchoua Syriane | D36: =IF(A36="","",TEXT(A36,"dddd")) -> 8/262026 | E36: =IF(A36="","",IFERROR(INDEX('00_Parametres'!$C$7:$C$13,WEEKDAY(A36,2)),"")) | F36: =IF(A36="","",IFERROR(INDEX('00_Parametres'!$D$7:$D$13,WEEKDAY(A36,2)),"")) | G36: =IF(A36="","",IFERROR(INDEX('00_Parametres'!$E$7:$E$13,WEEKDAY(A36,2)),0)) -> 0 | H36: 0.36805556 | J36: Non | K36: Non | L36: =IF(OR(A36="",H36=""),"",IF(H36<E36,IF(OR(J36="Oui",'00_Parametres'!$B$28="Oui"),H36,E36),H36)) | M36: =IF(OR(A36="",I36=""),"",IF(I36>F36,IF(OR(K36="Oui",'00_Parametres'!$B$29="Oui"),I36,F36),I36)) | N36: =IF(OR(A36="",H36="",E36=""),0,MAX(0,ROUND((H36-E36)*1440,0))) -> 0 | O36: =IF(OR(A36="",I36="",F36=""),0,MAX(0,ROUND((F36-I36)*1440,0))) -> 0 | P36: =IF(OR(L36="",M36=""),0,MAX(0,ROUND((M36-L36)*24-G36,2))) -> 0 | Q36: =IF(P36=0,0,MIN(P36,'00_Parametres'!$B$23)) -> 0 | R36: =IF(P36=0,0,MAX(0,P36-'00_Parametres'!$B$23)) -> 0
A37: 46260 | B37: EMP003 | C37: =IF(B37="","",IFERROR(VLOOKUP(B37,Employes[[ID]:[Nom Complet]],4,FALSE()),"")) -> Takoueta Yvan | D37: =IF(A37="","",TEXT(A37,"dddd")) -> 8/262026 | E37: =IF(A37="","",IFERROR(INDEX('00_Parametres'!$C$7:$C$13,WEEKDAY(A37,2)),"")) | F37: =IF(A37="","",IFERROR(INDEX('00_Parametres'!$D$7:$D$13,WEEKDAY(A37,2)),"")) | G37: =IF(A37="","",IFERROR(INDEX('00_Parametres'!$E$7:$E$13,WEEKDAY(A37,2)),0)) -> 0 | H37: 0.33333333 | J37: Non | K37: Non | L37: =IF(OR(A37="",H37=""),"",IF(H37<E37,IF(OR(J37="Oui",'00_Parametres'!$B$28="Oui"),H37,E37),H37)) | M37: =IF(OR(A37="",I37=""),"",IF(I37>F37,IF(OR(K37="Oui",'00_Parametres'!$B$29="Oui"),I37,F37),I37)) | N37: =IF(OR(A37="",H37="",E37=""),0,MAX(0,ROUND((H37-E37)*1440,0))) -> 0 | O37: =IF(OR(A37="",I37="",F37=""),0,MAX(0,ROUND((F37-I37)*1440,0))) -> 0 | P37: =IF(OR(L37="",M37=""),0,MAX(0,ROUND((M37-L37)*24-G37,2))) -> 0 | Q37: =IF(P37=0,0,MIN(P37,'00_Parametres'!$B$23)) -> 0 | R37: =IF(P37=0,0,MAX(0,P37-'00_Parametres'!$B$23)) -> 0
A38: 46260 | B38: EMP004 | C38: =IF(B38="","",IFERROR(VLOOKUP(B38,Employes[[ID]:[Nom Complet]],4,FALSE()),"")) -> Chekep Faustin | D38: =IF(A38="","",TEXT(A38,"dddd")) -> 8/262026 | E38: =IF(A38="","",IFERROR(INDEX('00_Parametres'!$C$7:$C$13,WEEKDAY(A38,2)),"")) | F38: =IF(A38="","",IFERROR(INDEX('00_Parametres'!$D$7:$D$13,WEEKDAY(A38,2)),"")) | G38: =IF(A38="","",IFERROR(INDEX('00_Parametres'!$E$7:$E$13,WEEKDAY(A38,2)),0)) -> 0 | H38: 0.3125 | J38: Non | K38: Non | L38: =IF(OR(A38="",H38=""),"",IF(H38<E38,IF(OR(J38="Oui",'00_Parametres'!$B$28="Oui"),H38,E38),H38)) | M38: =IF(OR(A38="",I38=""),"",IF(I38>F38,IF(OR(K38="Oui",'00_Parametres'!$B$29="Oui"),I38,F38),I38)) | N38: =IF(OR(A38="",H38="",E38=""),0,MAX(0,ROUND((H38-E38)*1440,0))) -> 0 | O38: =IF(OR(A38="",I38="",F38=""),0,MAX(0,ROUND((F38-I38)*1440,0))) -> 0 | P38: =IF(OR(L38="",M38=""),0,MAX(0,ROUND((M38-L38)*24-G38,2))) -> 0 | Q38: =IF(P38=0,0,MIN(P38,'00_Parametres'!$B$23)) -> 0 | R38: =IF(P38=0,0,MAX(0,P38-'00_Parametres'!$B$23)) -> 0
A39: 46260 | B39: EMP005 | C39: =IF(B39="","",IFERROR(VLOOKUP(B39,Employes[[ID]:[Nom Complet]],4,FALSE()),"")) -> Abdou | D39: =IF(A39="","",TEXT(A39,"dddd")) -> 8/262026 | E39: =IF(A39="","",IFERROR(INDEX('00_Parametres'!$C$7:$C$13,WEEKDAY(A39,2)),"")) | F39: =IF(A39="","",IFERROR(INDEX('00_Parametres'!$D$7:$D$13,WEEKDAY(A39,2)),"")) | G39: =IF(A39="","",IFERROR(INDEX('00_Parametres'!$E$7:$E$13,WEEKDAY(A39,2)),0)) -> 0 | H39: 0.33333333 | J39: Non | K39: Non | L39: =IF(OR(A39="",H39=""),"",IF(H39<E39,IF(OR(J39="Oui",'00_Parametres'!$B$28="Oui"),H39,E39),H39)) | M39: =IF(OR(A39="",I39=""),"",IF(I39>F39,IF(OR(K39="Oui",'00_Parametres'!$B$29="Oui"),I39,F39),I39)) | N39: =IF(OR(A39="",H39="",E39=""),0,MAX(0,ROUND((H39-E39)*1440,0))) -> 0 | O39: =IF(OR(A39="",I39="",F39=""),0,MAX(0,ROUND((F39-I39)*1440,0))) -> 0 | P39: =IF(OR(L39="",M39=""),0,MAX(0,ROUND((M39-L39)*24-G39,2))) -> 0 | Q39: =IF(P39=0,0,MIN(P39,'00_Parametres'!$B$23)) -> 0 | R39: =IF(P39=0,0,MAX(0,P39-'00_Parametres'!$B$23)) -> 0
A40: 46260 | B40: EMP006 | C40: =IF(B40="","",IFERROR(VLOOKUP(B40,Employes[[ID]:[Nom Complet]],4,FALSE()),"")) -> Nyontyen Si Jean Vinny | D40: =IF(A40="","",TEXT(A40,"dddd")) -> 8/262026 | E40: =IF(A40="","",IFERROR(INDEX('00_Parametres'!$C$7:$C$13,WEEKDAY(A40,2)),"")) | F40: =IF(A40="","",IFERROR(INDEX('00_Parametres'!$D$7:$D$13,WEEKDAY(A40,2)),"")) | G40: =IF(A40="","",IFERROR(INDEX('00_Parametres'!$E$7:$E$13,WEEKDAY(A40,2)),0)) -> 0 | H40: 0.35555556 | J40: Non | K40: Non | L40: =IF(OR(A40="",H40=""),"",IF(H40<E40,IF(OR(J40="Oui",'00_Parametres'!$B$28="Oui"),H40,E40),H40)) | M40: =IF(OR(A40="",I40=""),"",IF(I40>F40,IF(OR(K40="Oui",'00_Parametres'!$B$29="Oui"),I40,F40),I40)) | N40: =IF(OR(A40="",H40="",E40=""),0,MAX(0,ROUND((H40-E40)*1440,0))) -> 0 | O40: =IF(OR(A40="",I40="",F40=""),0,MAX(0,ROUND((F40-I40)*1440,0))) -> 0 | P40: =IF(OR(L40="",M40=""),0,MAX(0,ROUND((M40-L40)*24-G40,2))) -> 0 | Q40: =IF(P40=0,0,MIN(P40,'00_Parametres'!$B$23)) -> 0 | R40: =IF(P40=0,0,MAX(0,P40-'00_Parametres'!$B$23)) -> 0
A41: 46260 | B41: EMP007 | C41: =IF(B41="","",IFERROR(VLOOKUP(B41,Employes[[ID]:[Nom Complet]],4,FALSE()),"")) -> Holé Homsala | D41: =IF(A41="","",TEXT(A41,"dddd")) -> 8/262026 | E41: =IF(A41="","",IFERROR(INDEX('00_Parametres'!$C$7:$C$13,WEEKDAY(A41,2)),"")) | F41: =IF(A41="","",IFERROR(INDEX('00_Parametres'!$D$7:$D$13,WEEKDAY(A41,2)),"")) | G41: =IF(A41="","",IFERROR(INDEX('00_Parametres'!$E$7:$E$13,WEEKDAY(A41,2)),0)) -> 0 | H41: 0.36319444 | J41: Non | K41: Non | L41: =IF(OR(A41="",H41=""),"",IF(H41<E41,IF(OR(J41="Oui",'00_Parametres'!$B$28="Oui"),H41,E41),H41)) | M41: =IF(OR(A41="",I41=""),"",IF(I41>F41,IF(OR(K41="Oui",'00_Parametres'!$B$29="Oui"),I41,F41),I41)) | N41: =IF(OR(A41="",H41="",E41=""),0,MAX(0,ROUND((H41-E41)*1440,0))) -> 0 | O41: =IF(OR(A41="",I41="",F41=""),0,MAX(0,ROUND((F41-I41)*1440,0))) -> 0 | P41: =IF(OR(L41="",M41=""),0,MAX(0,ROUND((M41-L41)*24-G41,2))) -> 0 | Q41: =IF(P41=0,0,MIN(P41,'00_Parametres'!$B$23)) -> 0 | R41: =IF(P41=0,0,MAX(0,P41-'00_Parametres'!$B$23)) -> 0
A42: 46260 | B42: EMP008 | C42: =IF(B42="","",IFERROR(VLOOKUP(B42,Employes[[ID]:[Nom Complet]],4,FALSE()),"")) -> Ebene Ngono | D42: =IF(A42="","",TEXT(A42,"dddd")) -> 8/262026 | E42: =IF(A42="","",IFERROR(INDEX('00_Parametres'!$C$7:$C$13,WEEKDAY(A42,2)),"")) | F42: =IF(A42="","",IFERROR(INDEX('00_Parametres'!$D$7:$D$13,WEEKDAY(A42,2)),"")) | G42: =IF(A42="","",IFERROR(INDEX('00_Parametres'!$E$7:$E$13,WEEKDAY(A42,2)),0)) -> 0 | H42: 0.35416667 | J42: Non | K42: Non | L42: =IF(OR(A42="",H42=""),"",IF(H42<E42,IF(OR(J42="Oui",'00_Parametres'!$B$28="Oui"),H42,E42),H42)) | M42: =IF(OR(A42="",I42=""),"",IF(I42>F42,IF(OR(K42="Oui",'00_Parametres'!$B$29="Oui"),I42,F42),I42)) | N42: =IF(OR(A42="",H42="",E42=""),0,MAX(0,ROUND((H42-E42)*1440,0))) -> 0 | O42: =IF(OR(A42="",I42="",F42=""),0,MAX(0,ROUND((F42-I42)*1440,0))) -> 0 | P42: =IF(OR(L42="",M42=""),0,MAX(0,ROUND((M42-L42)*24-G42,2))) -> 0 | Q42: =IF(P42=0,0,MIN(P42,'00_Parametres'!$B$23)) -> 0 | R42: =IF(P42=0,0,MAX(0,P42-'00_Parametres'!$B$23)) -> 0
A43: 46260 | B43: EMP009 | C43: =IF(B43="","",IFERROR(VLOOKUP(B43,Employes[[ID]:[Nom Complet]],4,FALSE()),"")) -> Tineba Vital Eric | D43: =IF(A43="","",TEXT(A43,"dddd")) -> 8/262026 | E43: =IF(A43="","",IFERROR(INDEX('00_Parametres'!$C$7:$C$13,WEEKDAY(A43,2)),"")) | F43: =IF(A43="","",IFERROR(INDEX('00_Parametres'!$D$7:$D$13,WEEKDAY(A43,2)),"")) | G43: =IF(A43="","",IFERROR(INDEX('00_Parametres'!$E$7:$E$13,WEEKDAY(A43,2)),0)) -> 0 | H43: 0.35555556 | J43: Non | K43: Non | L43: =IF(OR(A43="",H43=""),"",IF(H43<E43,IF(OR(J43="Oui",'00_Parametres'!$B$28="Oui"),H43,E43),H43)) | M43: =IF(OR(A43="",I43=""),"",IF(I43>F43,IF(OR(K43="Oui",'00_Parametres'!$B$29="Oui"),I43,F43),I43)) | N43: =IF(OR(A43="",H43="",E43=""),0,MAX(0,ROUND((H43-E43)*1440,0))) -> 0 | O43: =IF(OR(A43="",I43="",F43=""),0,MAX(0,ROUND((F43-I43)*1440,0))) -> 0 | P43: =IF(OR(L43="",M43=""),0,MAX(0,ROUND((M43-L43)*24-G43,2))) -> 0 | Q43: =IF(P43=0,0,MIN(P43,'00_Parametres'!$B$23)) -> 0 | R43: =IF(P43=0,0,MAX(0,P43-'00_Parametres'!$B$23)) -> 0
A44: 46260 | B44: EMP010 | C44: =IF(B44="","",IFERROR(VLOOKUP(B44,Employes[[ID]:[Nom Complet]],4,FALSE()),"")) -> Deutchoua Tientcheu Christian | D44: =IF(A44="","",TEXT(A44,"dddd")) -> 8/262026 | E44: =IF(A44="","",IFERROR(INDEX('00_Parametres'!$C$7:$C$13,WEEKDAY(A44,2)),"")) | F44: =IF(A44="","",IFERROR(INDEX('00_Parametres'!$D$7:$D$13,WEEKDAY(A44,2)),"")) | G44: =IF(A44="","",IFERROR(INDEX('00_Parametres'!$E$7:$E$13,WEEKDAY(A44,2)),0)) -> 0 | J44: Non | K44: Non | L44: =IF(OR(A44="",H44=""),"",IF(H44<E44,IF(OR(J44="Oui",'00_Parametres'!$B$28="Oui"),H44,E44),H44)) | M44: =IF(OR(A44="",I44=""),"",IF(I44>F44,IF(OR(K44="Oui",'00_Parametres'!$B$29="Oui"),I44,F44),I44)) | N44: =IF(OR(A44="",H44="",E44=""),0,MAX(0,ROUND((H44-E44)*1440,0))) -> 0 | O44: =IF(OR(A44="",I44="",F44=""),0,MAX(0,ROUND((F44-I44)*1440,0))) -> 0 | P44: =IF(OR(L44="",M44=""),0,MAX(0,ROUND((M44-L44)*24-G44,2))) -> 0 | Q44: =IF(P44=0,0,MIN(P44,'00_Parametres'!$B$23)) -> 0 | R44: =IF(P44=0,0,MAX(0,P44-'00_Parametres'!$B$23)) -> 0
A45: 46260 | B45: EMP011 | C45: =IF(B45="","",IFERROR(VLOOKUP(B45,Employes[[ID]:[Nom Complet]],4,FALSE()),"")) -> Fouakouet Youssoufa | D45: =IF(A45="","",TEXT(A45,"dddd")) -> 8/262026 | E45: =IF(A45="","",IFERROR(INDEX('00_Parametres'!$C$7:$C$13,WEEKDAY(A45,2)),"")) | F45: =IF(A45="","",IFERROR(INDEX('00_Parametres'!$D$7:$D$13,WEEKDAY(A45,2)),"")) | G45: =IF(A45="","",IFERROR(INDEX('00_Parametres'!$E$7:$E$13,WEEKDAY(A45,2)),0)) -> 0 | H45: 0.35416667 | J45: Non | K45: Non | L45: =IF(OR(A45="",H45=""),"",IF(H45<E45,IF(OR(J45="Oui",'00_Parametres'!$B$28="Oui"),H45,E45),H45)) | M45: =IF(OR(A45="",I45=""),"",IF(I45>F45,IF(OR(K45="Oui",'00_Parametres'!$B$29="Oui"),I45,F45),I45)) | N45: =IF(OR(A45="",H45="",E45=""),0,MAX(0,ROUND((H45-E45)*1440,0))) -> 0 | O45: =IF(OR(A45="",I45="",F45=""),0,MAX(0,ROUND((F45-I45)*1440,0))) -> 0 | P45: =IF(OR(L45="",M45=""),0,MAX(0,ROUND((M45-L45)*24-G45,2))) -> 0 | Q45: =IF(P45=0,0,MIN(P45,'00_Parametres'!$B$23)) -> 0 | R45: =IF(P45=0,0,MAX(0,P45-'00_Parametres'!$B$23)) -> 0
A46: 46260 | B46: EMP012 | C46: =IF(B46="","",IFERROR(VLOOKUP(B46,Employes[[ID]:[Nom Complet]],4,FALSE()),"")) -> Ngouamera Adrien Gildas | D46: =IF(A46="","",TEXT(A46,"dddd")) -> 8/262026 | E46: =IF(A46="","",IFERROR(INDEX('00_Parametres'!$C$7:$C$13,WEEKDAY(A46,2)),"")) | F46: =IF(A46="","",IFERROR(INDEX('00_Parametres'!$D$7:$D$13,WEEKDAY(A46,2)),"")) | G46: =IF(A46="","",IFERROR(INDEX('00_Parametres'!$E$7:$E$13,WEEKDAY(A46,2)),0)) -> 0 | H46: 0.35763889 | J46: Non | K46: Non | L46: =IF(OR(A46="",H46=""),"",IF(H46<E46,IF(OR(J46="Oui",'00_Parametres'!$B$28="Oui"),H46,E46),H46)) | M46: =IF(OR(A46="",I46=""),"",IF(I46>F46,IF(OR(K46="Oui",'00_Parametres'!$B$29="Oui"),I46,F46),I46)) | N46: =IF(OR(A46="",H46="",E46=""),0,MAX(0,ROUND((H46-E46)*1440,0))) -> 0 | O46: =IF(OR(A46="",I46="",F46=""),0,MAX(0,ROUND((F46-I46)*1440,0))) -> 0 | P46: =IF(OR(L46="",M46=""),0,MAX(0,ROUND((M46-L46)*24-G46,2))) -> 0 | Q46: =IF(P46=0,0,MIN(P46,'00_Parametres'!$B$23)) -> 0 | R46: =IF(P46=0,0,MAX(0,P46-'00_Parametres'!$B$23)) -> 0
A47: 46260 | B47: EMP013 | C47: =IF(B47="","",IFERROR(VLOOKUP(B47,Employes[[ID]:[Nom Complet]],4,FALSE()),"")) -> Nague Zemdjui Arnaud | D47: =IF(A47="","",TEXT(A47,"dddd")) -> 8/262026 | E47: =IF(A47="","",IFERROR(INDEX('00_Parametres'!$C$7:$C$13,WEEKDAY(A47,2)),"")) | F47: =IF(A47="","",IFERROR(INDEX('00_Parametres'!$D$7:$D$13,WEEKDAY(A47,2)),"")) | G47: =IF(A47="","",IFERROR(INDEX('00_Parametres'!$E$7:$E$13,WEEKDAY(A47,2)),0)) -> 0 | H47: 0.30763889 | J47: Non | K47: Non | L47: =IF(OR(A47="",H47=""),"",IF(H47<E47,IF(OR(J47="Oui",'00_Parametres'!$B$28="Oui"),H47,E47),H47)) | M47: =IF(OR(A47="",I47=""),"",IF(I47>F47,IF(OR(K47="Oui",'00_Parametres'!$B$29="Oui"),I47,F47),I47)) | N47: =IF(OR(A47="",H47="",E47=""),0,MAX(0,ROUND((H47-E47)*1440,0))) -> 0 | O47: =IF(OR(A47="",I47="",F47=""),0,MAX(0,ROUND((F47-I47)*1440,0))) -> 0 | P47: =IF(OR(L47="",M47=""),0,MAX(0,ROUND((M47-L47)*24-G47,2))) -> 0 | Q47: =IF(P47=0,0,MIN(P47,'00_Parametres'!$B$23)) -> 0 | R47: =IF(P47=0,0,MAX(0,P47-'00_Parametres'!$B$23)) -> 0
A48: 46260 | B48: EMP014 | C48: =IF(B48="","",IFERROR(VLOOKUP(B48,Employes[[ID]:[Nom Complet]],4,FALSE()),"")) -> Zo'o Mbarga Jean Loic | D48: =IF(A48="","",TEXT(A48,"dddd")) -> 8/262026 | E48: =IF(A48="","",IFERROR(INDEX('00_Parametres'!$C$7:$C$13,WEEKDAY(A48,2)),"")) | F48: =IF(A48="","",IFERROR(INDEX('00_Parametres'!$D$7:$D$13,WEEKDAY(A48,2)),"")) | G48: =IF(A48="","",IFERROR(INDEX('00_Parametres'!$E$7:$E$13,WEEKDAY(A48,2)),0)) -> 0 | H48: 0.26319444 | J48: Non | K48: Non | L48: =IF(OR(A48="",H48=""),"",IF(H48<E48,IF(OR(J48="Oui",'00_Parametres'!$B$28="Oui"),H48,E48),H48)) | M48: =IF(OR(A48="",I48=""),"",IF(I48>F48,IF(OR(K48="Oui",'00_Parametres'!$B$29="Oui"),I48,F48),I48)) | N48: =IF(OR(A48="",H48="",E48=""),0,MAX(0,ROUND((H48-E48)*1440,0))) -> 0 | O48: =IF(OR(A48="",I48="",F48=""),0,MAX(0,ROUND((F48-I48)*1440,0))) -> 0 | P48: =IF(OR(L48="",M48=""),0,MAX(0,ROUND((M48-L48)*24-G48,2))) -> 0 | Q48: =IF(P48=0,0,MIN(P48,'00_Parametres'!$B$23)) -> 0 | R48: =IF(P48=0,0,MAX(0,P48-'00_Parametres'!$B$23)) -> 0
A49: 46260 | C49: =IF(B49="","",IFERROR(VLOOKUP(B49,Employes[[ID]:[Nom Complet]],4,FALSE()),"")) | D49: =IF(A49="","",TEXT(A49,"dddd")) -> 8/262026 | E49: =IF(A49="","",IFERROR(INDEX('00_Parametres'!$C$7:$C$13,WEEKDAY(A49,2)),"")) | F49: =IF(A49="","",IFERROR(INDEX('00_Parametres'!$D$7:$D$13,WEEKDAY(A49,2)),"")) | G49: =IF(A49="","",IFERROR(INDEX('00_Parametres'!$E$7:$E$13,WEEKDAY(A49,2)),0)) -> 0 | J49: Non | K49: Non | L49: =IF(OR(A49="",H49=""),"",IF(H49<E49,IF(OR(J49="Oui",'00_Parametres'!$B$28="Oui"),H49,E49),H49)) | M49: =IF(OR(A49="",I49=""),"",IF(I49>F49,IF(OR(K49="Oui",'00_Parametres'!$B$29="Oui"),I49,F49),I49)) | N49: =IF(OR(A49="",H49="",E49=""),0,MAX(0,ROUND((H49-E49)*1440,0))) -> 0 | O49: =IF(OR(A49="",I49="",F49=""),0,MAX(0,ROUND((F49-I49)*1440,0))) -> 0 | P49: =IF(OR(L49="",M49=""),0,MAX(0,ROUND((M49-L49)*24-G49,2))) -> 0 | Q49: =IF(P49=0,0,MIN(P49,'00_Parametres'!$B$23)) -> 0 | R49: =IF(P49=0,0,MAX(0,P49-'00_Parametres'!$B$23)) -> 0
C50: =IF(B50="","",IFERROR(VLOOKUP(B50,Employes[[ID]:[Nom Complet]],4,FALSE()),"")) | D50: =IF(A50="","",TEXT(A50,"dddd")) | E50: =IF(A50="","",IFERROR(INDEX('00_Parametres'!$C$7:$C$13,WEEKDAY(A50,2)),"")) | F50: =IF(A50="","",IFERROR(INDEX('00_Parametres'!$D$7:$D$13,WEEKDAY(A50,2)),"")) | G50: =IF(A50="","",IFERROR(INDEX('00_Parametres'!$E$7:$E$13,WEEKDAY(A50,2)),0)) | J50: Non | K50: Non | L50: =IF(OR(A50="",H50=""),"",IF(H50<E50,IF(OR(J50="Oui",'00_Parametres'!$B$28="Oui"),H50,E50),H50)) | M50: =IF(OR(A50="",I50=""),"",IF(I50>F50,IF(OR(K50="Oui",'00_Parametres'!$B$29="Oui"),I50,F50),I50)) | N50: =IF(OR(A50="",H50="",E50=""),0,MAX(0,ROUND((H50-E50)*1440,0))) -> 0 | O50: =IF(OR(A50="",I50="",F50=""),0,MAX(0,ROUND((F50-I50)*1440,0))) -> 0 | P50: =IF(OR(L50="",M50=""),0,MAX(0,ROUND((M50-L50)*24-G50,2))) -> 0 | Q50: =IF(P50=0,0,MIN(P50,'00_Parametres'!$B$23)) -> 0 | R50: =IF(P50=0,0,MAX(0,P50-'00_Parametres'!$B$23)) -> 0
C51: =IF(B51="","",IFERROR(VLOOKUP(B51,Employes[[ID]:[Nom Complet]],4,FALSE()),"")) | D51: =IF(A51="","",TEXT(A51,"dddd")) | E51: =IF(A51="","",IFERROR(INDEX('00_Parametres'!$C$7:$C$13,WEEKDAY(A51,2)),"")) | F51: =IF(A51="","",IFERROR(INDEX('00_Parametres'!$D$7:$D$13,WEEKDAY(A51,2)),"")) | G51: =IF(A51="","",IFERROR(INDEX('00_Parametres'!$E$7:$E$13,WEEKDAY(A51,2)),0)) | J51: Non | K51: Non | L51: =IF(OR(A51="",H51=""),"",IF(H51<E51,IF(OR(J51="Oui",'00_Parametres'!$B$28="Oui"),H51,E51),H51)) | M51: =IF(OR(A51="",I51=""),"",IF(I51>F51,IF(OR(K51="Oui",'00_Parametres'!$B$29="Oui"),I51,F51),I51)) | N51: =IF(OR(A51="",H51="",E51=""),0,MAX(0,ROUND((H51-E51)*1440,0))) -> 0 | O51: =IF(OR(A51="",I51="",F51=""),0,MAX(0,ROUND((F51-I51)*1440,0))) -> 0 | P51: =IF(OR(L51="",M51=""),0,MAX(0,ROUND((M51-L51)*24-G51,2))) -> 0 | Q51: =IF(P51=0,0,MIN(P51,'00_Parametres'!$B$23)) -> 0 | R51: =IF(P51=0,0,MAX(0,P51-'00_Parametres'!$B$23)) -> 0
C52: =IF(B52="","",IFERROR(VLOOKUP(B52,Employes[[ID]:[Nom Complet]],4,FALSE()),"")) | D52: =IF(A52="","",TEXT(A52,"dddd")) | E52: =IF(A52="","",IFERROR(INDEX('00_Parametres'!$C$7:$C$13,WEEKDAY(A52,2)),"")) | F52: =IF(A52="","",IFERROR(INDEX('00_Parametres'!$D$7:$D$13,WEEKDAY(A52,2)),"")) | G52: =IF(A52="","",IFERROR(INDEX('00_Parametres'!$E$7:$E$13,WEEKDAY(A52,2)),0)) | J52: Non | K52: Non | L52: =IF(OR(A52="",H52=""),"",IF(H52<E52,IF(OR(J52="Oui",'00_Parametres'!$B$28="Oui"),H52,E52),H52)) | M52: =IF(OR(A52="",I52=""),"",IF(I52>F52,IF(OR(K52="Oui",'00_Parametres'!$B$29="Oui"),I52,F52),I52)) | N52: =IF(OR(A52="",H52="",E52=""),0,MAX(0,ROUND((H52-E52)*1440,0))) -> 0 | O52: =IF(OR(A52="",I52="",F52=""),0,MAX(0,ROUND((F52-I52)*1440,0))) -> 0 | P52: =IF(OR(L52="",M52=""),0,MAX(0,ROUND((M52-L52)*24-G52,2))) -> 0 | Q52: =IF(P52=0,0,MIN(P52,'00_Parametres'!$B$23)) -> 0 | R52: =IF(P52=0,0,MAX(0,P52-'00_Parametres'!$B$23)) -> 0
C53: =IF(B53="","",IFERROR(VLOOKUP(B53,Employes[[ID]:[Nom Complet]],4,FALSE()),"")) | D53: =IF(A53="","",TEXT(A53,"dddd")) | E53: =IF(A53="","",IFERROR(INDEX('00_Parametres'!$C$7:$C$13,WEEKDAY(A53,2)),"")) | F53: =IF(A53="","",IFERROR(INDEX('00_Parametres'!$D$7:$D$13,WEEKDAY(A53,2)),"")) | G53: =IF(A53="","",IFERROR(INDEX('00_Parametres'!$E$7:$E$13,WEEKDAY(A53,2)),0)) | J53: Non | K53: Non | L53: =IF(OR(A53="",H53=""),"",IF(H53<E53,IF(OR(J53="Oui",'00_Parametres'!$B$28="Oui"),H53,E53),H53)) | M53: =IF(OR(A53="",I53=""),"",IF(I53>F53,IF(OR(K53="Oui",'00_Parametres'!$B$29="Oui"),I53,F53),I53)) | N53: =IF(OR(A53="",H53="",E53=""),0,MAX(0,ROUND((H53-E53)*1440,0))) -> 0 | O53: =IF(OR(A53="",I53="",F53=""),0,MAX(0,ROUND((F53-I53)*1440,0))) -> 0 | P53: =IF(OR(L53="",M53=""),0,MAX(0,ROUND((M53-L53)*24-G53,2))) -> 0 | Q53: =IF(P53=0,0,MIN(P53,'00_Parametres'!$B$23)) -> 0 | R53: =IF(P53=0,0,MAX(0,P53-'00_Parametres'!$B$23)) -> 0
C54: =IF(B54="","",IFERROR(VLOOKUP(B54,Employes[[ID]:[Nom Complet]],4,FALSE()),"")) | D54: =IF(A54="","",TEXT(A54,"dddd")) | E54: =IF(A54="","",IFERROR(INDEX('00_Parametres'!$C$7:$C$13,WEEKDAY(A54,2)),"")) | F54: =IF(A54="","",IFERROR(INDEX('00_Parametres'!$D$7:$D$13,WEEKDAY(A54,2)),"")) | G54: =IF(A54="","",IFERROR(INDEX('00_Parametres'!$E$7:$E$13,WEEKDAY(A54,2)),0)) | J54: Non | K54: Non | L54: =IF(OR(A54="",H54=""),"",IF(H54<E54,IF(OR(J54="Oui",'00_Parametres'!$B$28="Oui"),H54,E54),H54)) | M54: =IF(OR(A54="",I54=""),"",IF(I54>F54,IF(OR(K54="Oui",'00_Parametres'!$B$29="Oui"),I54,F54),I54)) | N54: =IF(OR(A54="",H54="",E54=""),0,MAX(0,ROUND((H54-E54)*1440,0))) -> 0 | O54: =IF(OR(A54="",I54="",F54=""),0,MAX(0,ROUND((F54-I54)*1440,0))) -> 0 | P54: =IF(OR(L54="",M54=""),0,MAX(0,ROUND((M54-L54)*24-G54,2))) -> 0 | Q54: =IF(P54=0,0,MIN(P54,'00_Parametres'!$B$23)) -> 0 | R54: =IF(P54=0,0,MAX(0,P54-'00_Parametres'!$B$23)) -> 0
C55: =IF(B55="","",IFERROR(VLOOKUP(B55,Employes[[ID]:[Nom Complet]],4,FALSE()),"")) | D55: =IF(A55="","",TEXT(A55,"dddd")) | E55: =IF(A55="","",IFERROR(INDEX('00_Parametres'!$C$7:$C$13,WEEKDAY(A55,2)),"")) | F55: =IF(A55="","",IFERROR(INDEX('00_Parametres'!$D$7:$D$13,WEEKDAY(A55,2)),"")) | G55: =IF(A55="","",IFERROR(INDEX('00_Parametres'!$E$7:$E$13,WEEKDAY(A55,2)),0)) | J55: Non | K55: Non | L55: =IF(OR(A55="",H55=""),"",IF(H55<E55,IF(OR(J55="Oui",'00_Parametres'!$B$28="Oui"),H55,E55),H55)) | M55: =IF(OR(A55="",I55=""),"",IF(I55>F55,IF(OR(K55="Oui",'00_Parametres'!$B$29="Oui"),I55,F55),I55)) | N55: =IF(OR(A55="",H55="",E55=""),0,MAX(0,ROUND((H55-E55)*1440,0))) -> 0 | O55: =IF(OR(A55="",I55="",F55=""),0,MAX(0,ROUND((F55-I55)*1440,0))) -> 0 | P55: =IF(OR(L55="",M55=""),0,MAX(0,ROUND((M55-L55)*24-G55,2))) -> 0 | Q55: =IF(P55=0,0,MIN(P55,'00_Parametres'!$B$23)) -> 0 | R55: =IF(P55=0,0,MAX(0,P55-'00_Parametres'!$B$23)) -> 0
C56: =IF(B56="","",IFERROR(VLOOKUP(B56,Employes[[ID]:[Nom Complet]],4,FALSE()),"")) | D56: =IF(A56="","",TEXT(A56,"dddd")) | E56: =IF(A56="","",IFERROR(INDEX('00_Parametres'!$C$7:$C$13,WEEKDAY(A56,2)),"")) | F56: =IF(A56="","",IFERROR(INDEX('00_Parametres'!$D$7:$D$13,WEEKDAY(A56,2)),"")) | G56: =IF(A56="","",IFERROR(INDEX('00_Parametres'!$E$7:$E$13,WEEKDAY(A56,2)),0)) | J56: Non | K56: Non | L56: =IF(OR(A56="",H56=""),"",IF(H56<E56,IF(OR(J56="Oui",'00_Parametres'!$B$28="Oui"),H56,E56),H56)) | M56: =IF(OR(A56="",I56=""),"",IF(I56>F56,IF(OR(K56="Oui",'00_Parametres'!$B$29="Oui"),I56,F56),I56)) | N56: =IF(OR(A56="",H56="",E56=""),0,MAX(0,ROUND((H56-E56)*1440,0))) -> 0 | O56: =IF(OR(A56="",I56="",F56=""),0,MAX(0,ROUND((F56-I56)*1440,0))) -> 0 | P56: =IF(OR(L56="",M56=""),0,MAX(0,ROUND((M56-L56)*24-G56,2))) -> 0 | Q56: =IF(P56=0,0,MIN(P56,'00_Parametres'!$B$23)) -> 0 | R56: =IF(P56=0,0,MAX(0,P56-'00_Parametres'!$B$23)) -> 0
C57: =IF(B57="","",IFERROR(VLOOKUP(B57,Employes[[ID]:[Nom Complet]],4,FALSE()),"")) | D57: =IF(A57="","",TEXT(A57,"dddd")) | E57: =IF(A57="","",IFERROR(INDEX('00_Parametres'!$C$7:$C$13,WEEKDAY(A57,2)),"")) | F57: =IF(A57="","",IFERROR(INDEX('00_Parametres'!$D$7:$D$13,WEEKDAY(A57,2)),"")) | G57: =IF(A57="","",IFERROR(INDEX('00_Parametres'!$E$7:$E$13,WEEKDAY(A57,2)),0)) | J57: Non | K57: Non | L57: =IF(OR(A57="",H57=""),"",IF(H57<E57,IF(OR(J57="Oui",'00_Parametres'!$B$28="Oui"),H57,E57),H57)) | M57: =IF(OR(A57="",I57=""),"",IF(I57>F57,IF(OR(K57="Oui",'00_Parametres'!$B$29="Oui"),I57,F57),I57)) | N57: =IF(OR(A57="",H57="",E57=""),0,MAX(0,ROUND((H57-E57)*1440,0))) -> 0 | O57: =IF(OR(A57="",I57="",F57=""),0,MAX(0,ROUND((F57-I57)*1440,0))) -> 0 | P57: =IF(OR(L57="",M57=""),0,MAX(0,ROUND((M57-L57)*24-G57,2))) -> 0 | Q57: =IF(P57=0,0,MIN(P57,'00_Parametres'!$B$23)) -> 0 | R57: =IF(P57=0,0,MAX(0,P57-'00_Parametres'!$B$23)) -> 0
C58: =IF(B58="","",IFERROR(VLOOKUP(B58,Employes[[ID]:[Nom Complet]],4,FALSE()),"")) | D58: =IF(A58="","",TEXT(A58,"dddd")) | E58: =IF(A58="","",IFERROR(INDEX('00_Parametres'!$C$7:$C$13,WEEKDAY(A58,2)),"")) | F58: =IF(A58="","",IFERROR(INDEX('00_Parametres'!$D$7:$D$13,WEEKDAY(A58,2)),"")) | G58: =IF(A58="","",IFERROR(INDEX('00_Parametres'!$E$7:$E$13,WEEKDAY(A58,2)),0)) | J58: Non | K58: Non | L58: =IF(OR(A58="",H58=""),"",IF(H58<E58,IF(OR(J58="Oui",'00_Parametres'!$B$28="Oui"),H58,E58),H58)) | M58: =IF(OR(A58="",I58=""),"",IF(I58>F58,IF(OR(K58="Oui",'00_Parametres'!$B$29="Oui"),I58,F58),I58)) | N58: =IF(OR(A58="",H58="",E58=""),0,MAX(0,ROUND((H58-E58)*1440,0))) -> 0 | O58: =IF(OR(A58="",I58="",F58=""),0,MAX(0,ROUND((F58-I58)*1440,0))) -> 0 | P58: =IF(OR(L58="",M58=""),0,MAX(0,ROUND((M58-L58)*24-G58,2))) -> 0 | Q58: =IF(P58=0,0,MIN(P58,'00_Parametres'!$B$23)) -> 0 | R58: =IF(P58=0,0,MAX(0,P58-'00_Parametres'!$B$23)) -> 0
C59: =IF(B59="","",IFERROR(VLOOKUP(B59,Employes[[ID]:[Nom Complet]],4,FALSE()),"")) | D59: =IF(A59="","",TEXT(A59,"dddd")) | E59: =IF(A59="","",IFERROR(INDEX('00_Parametres'!$C$7:$C$13,WEEKDAY(A59,2)),"")) | F59: =IF(A59="","",IFERROR(INDEX('00_Parametres'!$D$7:$D$13,WEEKDAY(A59,2)),"")) | G59: =IF(A59="","",IFERROR(INDEX('00_Parametres'!$E$7:$E$13,WEEKDAY(A59,2)),0)) | J59: Non | K59: Non | L59: =IF(OR(A59="",H59=""),"",IF(H59<E59,IF(OR(J59="Oui",'00_Parametres'!$B$28="Oui"),H59,E59),H59)) | M59: =IF(OR(A59="",I59=""),"",IF(I59>F59,IF(OR(K59="Oui",'00_Parametres'!$B$29="Oui"),I59,F59),I59)) | N59: =IF(OR(A59="",H59="",E59=""),0,MAX(0,ROUND((H59-E59)*1440,0))) -> 0 | O59: =IF(OR(A59="",I59="",F59=""),0,MAX(0,ROUND((F59-I59)*1440,0))) -> 0 | P59: =IF(OR(L59="",M59=""),0,MAX(0,ROUND((M59-L59)*24-G59,2))) -> 0 | Q59: =IF(P59=0,0,MIN(P59,'00_Parametres'!$B$23)) -> 0 | R59: =IF(P59=0,0,MAX(0,P59-'00_Parametres'!$B$23)) -> 0
C60: =IF(B60="","",IFERROR(VLOOKUP(B60,Employes[[ID]:[Nom Complet]],4,FALSE()),"")) | D60: =IF(A60="","",TEXT(A60,"dddd")) | E60: =IF(A60="","",IFERROR(INDEX('00_Parametres'!$C$7:$C$13,WEEKDAY(A60,2)),"")) | F60: =IF(A60="","",IFERROR(INDEX('00_Parametres'!$D$7:$D$13,WEEKDAY(A60,2)),"")) | G60: =IF(A60="","",IFERROR(INDEX('00_Parametres'!$E$7:$E$13,WEEKDAY(A60,2)),0)) | J60: Non | K60: Non | L60: =IF(OR(A60="",H60=""),"",IF(H60<E60,IF(OR(J60="Oui",'00_Parametres'!$B$28="Oui"),H60,E60),H60)) | M60: =IF(OR(A60="",I60=""),"",IF(I60>F60,IF(OR(K60="Oui",'00_Parametres'!$B$29="Oui"),I60,F60),I60)) | N60: =IF(OR(A60="",H60="",E60=""),0,MAX(0,ROUND((H60-E60)*1440,0))) -> 0 | O60: =IF(OR(A60="",I60="",F60=""),0,MAX(0,ROUND((F60-I60)*1440,0))) -> 0 | P60: =IF(OR(L60="",M60=""),0,MAX(0,ROUND((M60-L60)*24-G60,2))) -> 0 | Q60: =IF(P60=0,0,MIN(P60,'00_Parametres'!$B$23)) -> 0 | R60: =IF(P60=0,0,MAX(0,P60-'00_Parametres'!$B$23)) -> 0
C61: =IF(B61="","",IFERROR(VLOOKUP(B61,Employes[[ID]:[Nom Complet]],4,FALSE()),"")) | D61: =IF(A61="","",TEXT(A61,"dddd")) | E61: =IF(A61="","",IFERROR(INDEX('00_Parametres'!$C$7:$C$13,WEEKDAY(A61,2)),"")) | F61: =IF(A61="","",IFERROR(INDEX('00_Parametres'!$D$7:$D$13,WEEKDAY(A61,2)),"")) | G61: =IF(A61="","",IFERROR(INDEX('00_Parametres'!$E$7:$E$13,WEEKDAY(A61,2)),0)) | J61: Non | K61: Non | L61: =IF(OR(A61="",H61=""),"",IF(H61<E61,IF(OR(J61="Oui",'00_Parametres'!$B$28="Oui"),H61,E61),H61)) | M61: =IF(OR(A61="",I61=""),"",IF(I61>F61,IF(OR(K61="Oui",'00_Parametres'!$B$29="Oui"),I61,F61),I61)) | N61: =IF(OR(A61="",H61="",E61=""),0,MAX(0,ROUND((H61-E61)*1440,0))) -> 0 | O61: =IF(OR(A61="",I61="",F61=""),0,MAX(0,ROUND((F61-I61)*1440,0))) -> 0 | P61: =IF(OR(L61="",M61=""),0,MAX(0,ROUND((M61-L61)*24-G61,2))) -> 0 | Q61: =IF(P61=0,0,MIN(P61,'00_Parametres'!$B$23)) -> 0 | R61: =IF(P61=0,0,MAX(0,P61-'00_Parametres'!$B$23)) -> 0
... C150: =IF(B150="","",IFERROR(VLOOKUP(B150,Employes[[ID]:[Nom Complet]],4,FALSE()),"")) | D150: =IF(A150="","",TEXT(A150,"dddd")) | E150: =IF(A150="","",IFERROR(INDEX('00_Parametres'!$C$7:$C$13,WEEKDAY(A150,2)),"")) | F150: =IF(A150="","",IFERROR(INDEX('00_Parametres'!$D$7:$D$13,WEEKDAY(A150,2)),"")) | G150: =IF(A150="","",IFERROR(INDEX('00_Parametres'!$E$7:$E$13,WEEKDAY(A150,2)),0)) | J150: Non | K150: Non | L150: =IF(OR(A150="",H150=""),"",IF(H150<E150,IF(OR(J150="Oui",'00_Parametres'!$B$28="Oui"),H150,E150),H150)) | M150: =IF(OR(A150="",I150=""),"",IF(I150>F150,IF(OR(K150="Oui",'00_Parametres'!$B$29="Oui"),I150,F150),I150)) | N150: =IF(OR(A150="",H150="",E150=""),0,MAX(0,ROUND((H150-E150)*1440,0))) -> 0 | O150: =IF(OR(A150="",I150="",F150=""),0,MAX(0,ROUND((F150-I150)*1440,0))) -> 0 | P150: =IF(OR(L150="",M150=""),0,MAX(0,ROUND((M150-L150)*24-G150,2))) -> 0 | Q150: =IF(P150=0,0,MIN(P150,'00_Parametres'!$B$23)) -> 0 | R150: =IF(P150=0,0,MAX(0,P150-'00_Parametres'!$B$23)) -> 0

Sheet 03_Paie
A1: CALCUL DE PAIE — BASÉ SUR LES HEURES RÉELLES + PRIMES DE TÂCHE
A2: Sélectionnez la période. Les heures, primes et salaires se calculent automatiquement à partir du Pointage et des paramètres employés.
A4: PÉRIODE DE CALCUL
A5: Date début | B5: 46235 | C5: Date fin | D5: 46265 | E5: ← Modifiez ces dates pour recalculer sur n'importe quelle période
A7: SYNTHÈSE PÉRIODE
A8: Total Heures Normales | B8: =G27 -> 164.12 | C8: Total Heures Supp | D8: =H27 -> 1 | E8: Total Primes Tâches | F8: =I27 -> 7500 | G8: Masse Salariale Estimée | H8: =L27 -> 86433
A11: ID | B11: Nom Complet | C11: Poste | D11: Type Contrat | E11: Salaire Base Mensuel | F11: Taux Horaire | G11: Heures Normales | H11: Heures Supp. | I11: Total Primes Tâches | J11: Montant Heures Normales | K11: Montant HS | L11: Salaire Brut Estimé | M11: Jours Présents | N11: Observations
A12: =IF('01_Employes'!A6="","",'01_Employes'!A6) -> EMP001 | B12: =IF(A12="","",'01_Employes'!D6) -> Tsafack Ndongmo Symphonien | C12: =IF(A12="","",'01_Employes'!E6) -> Administrateur | D12: =IF(A12="","",'01_Employes'!K6) -> CDI | E12: =IF(A12="","",'01_Employes'!L6) -> 150000 | F12: =IF(A12="","",'01_Employes'!M6) -> 666 | G12: =IF(A12="","",SUMIFS(Pointage[Heures Normales],Pointage[ID Employé],A12,Pointage[Date],">="&$B$5,Pointage[Date],"<="&$D$5)) -> 16.83 | H12: =IF(A12="","",SUMIFS(Pointage[Heures Supp.],Pointage[ID Employé],A12,Pointage[Date],">="&$B$5,Pointage[Date],"<="&$D$5)) -> 0 | I12: =IF(A12="","",SUMIFS(Pointage[Prime Tâche (FCFA)],Pointage[ID Employé],A12,Pointage[Date],">="&$B$5,Pointage[Date],"<="&$D$5)) -> 0 | J12: =IF(OR(A12="",F12=""),0,ROUND(G12*F12,0)) -> 11209 | K12: =IF(OR(A12="",H12=""),0,ROUND(H12*'01_Employes'!N6,0)) -> 0 | L12: =IF(A12="","",J12+K12+I12) -> 11209 | M12: =IF(A12="","",COUNTIFS(Pointage[ID Employé],A12,Pointage[Date],">="&$B$5,Pointage[Date],"<="&$D$5,Pointage[Heures travaillées],">0")) -> 2
A13: =IF('01_Employes'!A7="","",'01_Employes'!A7) -> EMP002 | B13: =IF(A13="","",'01_Employes'!D7) -> Pandja Tchatchoua Syriane | C13: =IF(A13="","",'01_Employes'!E7) -> Secrétaire | D13: =IF(A13="","",'01_Employes'!K7) -> CDI | E13: =IF(A13="","",'01_Employes'!L7) -> 100000 | F13: =IF(A13="","",'01_Employes'!M7) -> 444 | G13: =IF(A13="","",SUMIFS(Pointage[Heures Normales],Pointage[ID Employé],A13,Pointage[Date],">="&$B$5,Pointage[Date],"<="&$D$5)) -> 15 | H13: =IF(A13="","",SUMIFS(Pointage[Heures Supp.],Pointage[ID Employé],A13,Pointage[Date],">="&$B$5,Pointage[Date],"<="&$D$5)) -> 1 | I13: =IF(A13="","",SUMIFS(Pointage[Prime Tâche (FCFA)],Pointage[ID Employé],A13,Pointage[Date],">="&$B$5,Pointage[Date],"<="&$D$5)) -> 5000 | J13: =IF(OR(A13="",F13=""),0,ROUND(G13*F13,0)) -> 6660 | K13: =IF(OR(A13="",H13=""),0,ROUND(H13*'01_Employes'!N7,0)) -> 666 | L13: =IF(A13="","",J13+K13+I13) -> 12326 | M13: =IF(A13="","",COUNTIFS(Pointage[ID Employé],A13,Pointage[Date],">="&$B$5,Pointage[Date],"<="&$D$5,Pointage[Heures travaillées],">0")) -> 2
A14: =IF('01_Employes'!A8="","",'01_Employes'!A8) -> EMP003 | B14: =IF(A14="","",'01_Employes'!D8) -> Takoueta Yvan | C14: =IF(A14="","",'01_Employes'!E8) -> Chef des ateliers | D14: =IF(A14="","",'01_Employes'!K8) -> CDI | E14: =IF(A14="","",'01_Employes'!L8) -> 150000 | F14: =IF(A14="","",'01_Employes'!M8) -> 666 | G14: =IF(A14="","",SUMIFS(Pointage[Heures Normales],Pointage[ID Employé],A14,Pointage[Date],">="&$B$5,Pointage[Date],"<="&$D$5)) -> 16.5 | H14: =IF(A14="","",SUMIFS(Pointage[Heures Supp.],Pointage[ID Employé],A14,Pointage[Date],">="&$B$5,Pointage[Date],"<="&$D$5)) -> 0 | I14: =IF(A14="","",SUMIFS(Pointage[Prime Tâche (FCFA)],Pointage[ID Employé],A14,Pointage[Date],">="&$B$5,Pointage[Date],"<="&$D$5)) -> 0 | J14: =IF(OR(A14="",F14=""),0,ROUND(G14*F14,0)) -> 10989 | K14: =IF(OR(A14="",H14=""),0,ROUND(H14*'01_Employes'!N8,0)) -> 0 | L14: =IF(A14="","",J14+K14+I14) -> 10989 | M14: =IF(A14="","",COUNTIFS(Pointage[ID Employé],A14,Pointage[Date],">="&$B$5,Pointage[Date],"<="&$D$5,Pointage[Heures travaillées],">0")) -> 2
A15: =IF('01_Employes'!A9="","",'01_Employes'!A9) -> EMP004 | B15: =IF(A15="","",'01_Employes'!D9) -> Chekep Faustin | C15: =IF(A15="","",'01_Employes'!E9) -> Mécanicien | D15: =IF(A15="","",'01_Employes'!K9) -> CDI | E15: =IF(A15="","",'01_Employes'!L9) -> 120000 | F15: =IF(A15="","",'01_Employes'!M9) -> 533 | G15: =IF(A15="","",SUMIFS(Pointage[Heures Normales],Pointage[ID Employé],A15,Pointage[Date],">="&$B$5,Pointage[Date],"<="&$D$5)) -> 18.2 | H15: =IF(A15="","",SUMIFS(Pointage[Heures Supp.],Pointage[ID Employé],A15,Pointage[Date],">="&$B$5,Pointage[Date],"<="&$D$5)) -> 0 | I15: =IF(A15="","",SUMIFS(Pointage[Prime Tâche (FCFA)],Pointage[ID Employé],A15,Pointage[Date],">="&$B$5,Pointage[Date],"<="&$D$5)) -> 0 | J15: =IF(OR(A15="",F15=""),0,ROUND(G15*F15,0)) -> 9701 | K15: =IF(OR(A15="",H15=""),0,ROUND(H15*'01_Employes'!N9,0)) -> 0 | L15: =IF(A15="","",J15+K15+I15) -> 9701 | M15: =IF(A15="","",COUNTIFS(Pointage[ID Employé],A15,Pointage[Date],">="&$B$5,Pointage[Date],"<="&$D$5,Pointage[Heures travaillées],">0")) -> 2
A16: =IF('01_Employes'!A10="","",'01_Employes'!A10) -> EMP005 | B16: =IF(A16="","",'01_Employes'!D10) -> Abdou | C16: =IF(A16="","",'01_Employes'!E10) -> Tôlier | D16: =IF(A16="","",'01_Employes'!K10) -> Apprentissage | E16: =IF(A16="","",'01_Employes'!L10) -> 80000 | F16: =IF(A16="","",'01_Employes'!M10) -> 355 | G16: =IF(A16="","",SUMIFS(Pointage[Heures Normales],Pointage[ID Employé],A16,Pointage[Date],">="&$B$5,Pointage[Date],"<="&$D$5)) -> 12.5 | H16: =IF(A16="","",SUMIFS(Pointage[Heures Supp.],Pointage[ID Employé],A16,Pointage[Date],">="&$B$5,Pointage[Date],"<="&$D$5)) -> 0 | I16: =IF(A16="","",SUMIFS(Pointage[Prime Tâche (FCFA)],Pointage[ID Employé],A16,Pointage[Date],">="&$B$5,Pointage[Date],"<="&$D$5)) -> 2500 | J16: =IF(OR(A16="",F16=""),0,ROUND(G16*F16,0)) -> 4438 | K16: =IF(OR(A16="",H16=""),0,ROUND(H16*'01_Employes'!N10,0)) -> 0 | L16: =IF(A16="","",J16+K16+I16) -> 6938 | M16: =IF(A16="","",COUNTIFS(Pointage[ID Employé],A16,Pointage[Date],">="&$B$5,Pointage[Date],"<="&$D$5,Pointage[Heures travaillées],">0")) -> 2
A17: =IF('01_Employes'!A11="","",'01_Employes'!A11) -> EMP006 | B17: =IF(A17="","",'01_Employes'!D11) -> Nyontyen Si Jean Vinny | C17: =IF(A17="","",'01_Employes'!E11) -> Mécanicien | D17: =IF(A17="","",'01_Employes'!K11) -> Apprentissage | E17: =IF(A17="","",'01_Employes'!L11) -> 80000 | F17: =IF(A17="","",'01_Employes'!M11) -> 355 | G17: =IF(A17="","",SUMIFS(Pointage[Heures Normales],Pointage[ID Employé],A17,Pointage[Date],">="&$B$5,Pointage[Date],"<="&$D$5)) -> 18.15 | H17: =IF(A17="","",SUMIFS(Pointage[Heures Supp.],Pointage[ID Employé],A17,Pointage[Date],">="&$B$5,Pointage[Date],"<="&$D$5)) -> 0 | I17: =IF(A17="","",SUMIFS(Pointage[Prime Tâche (FCFA)],Pointage[ID Employé],A17,Pointage[Date],">="&$B$5,Pointage[Date],"<="&$D$5)) -> 0 | J17: =IF(OR(A17="",F17=""),0,ROUND(G17*F17,0)) -> 6443 | K17: =IF(OR(A17="",H17=""),0,ROUND(H17*'01_Employes'!N11,0)) -> 0 | L17: =IF(A17="","",J17+K17+I17) -> 6443 | M17: =IF(A17="","",COUNTIFS(Pointage[ID Employé],A17,Pointage[Date],">="&$B$5,Pointage[Date],"<="&$D$5,Pointage[Heures travaillées],">0")) -> 2
A18: =IF('01_Employes'!A12="","",'01_Employes'!A12) -> EMP007 | B18: =IF(A18="","",'01_Employes'!D12) -> Holé Homsala | C18: =IF(A18="","",'01_Employes'!E12) -> Magasinier | D18: =IF(A18="","",'01_Employes'!K12) -> Apprentissage | E18: =IF(A18="","",'01_Employes'!L12) -> 80000 | F18: =IF(A18="","",'01_Employes'!M12) -> 355 | G18: =IF(A18="","",SUMIFS(Pointage[Heures Normales],Pointage[ID Employé],A18,Pointage[Date],">="&$B$5,Pointage[Date],"<="&$D$5)) -> 9.43 | H18: =IF(A18="","",SUMIFS(Pointage[Heures Supp.],Pointage[ID Employé],A18,Pointage[Date],">="&$B$5,Pointage[Date],"<="&$D$5)) -> 0 | I18: =IF(A18="","",SUMIFS(Pointage[Prime Tâche (FCFA)],Pointage[ID Employé],A18,Pointage[Date],">="&$B$5,Pointage[Date],"<="&$D$5)) -> 0 | J18: =IF(OR(A18="",F18=""),0,ROUND(G18*F18,0)) -> 3348 | K18: =IF(OR(A18="",H18=""),0,ROUND(H18*'01_Employes'!N12,0)) -> 0 | L18: =IF(A18="","",J18+K18+I18) -> 3348 | M18: =IF(A18="","",COUNTIFS(Pointage[ID Employé],A18,Pointage[Date],">="&$B$5,Pointage[Date],"<="&$D$5,Pointage[Heures travaillées],">0")) -> 2
A19: =IF('01_Employes'!A13="","",'01_Employes'!A13) -> EMP008 | B19: =IF(A19="","",'01_Employes'!D13) -> Ebene Ngono | C19: =IF(A19="","",'01_Employes'!E13) -> Mécanicien | D19: =IF(A19="","",'01_Employes'!K13) -> Apprentissage | E19: =IF(A19="","",'01_Employes'!L13) -> 80000 | F19: =IF(A19="","",'01_Employes'!M13) -> 355 | G19: =IF(A19="","",SUMIFS(Pointage[Heures Normales],Pointage[ID Employé],A19,Pointage[Date],">="&$B$5,Pointage[Date],"<="&$D$5)) -> 9.33 | H19: =IF(A19="","",SUMIFS(Pointage[Heures Supp.],Pointage[ID Employé],A19,Pointage[Date],">="&$B$5,Pointage[Date],"<="&$D$5)) -> 0 | I19: =IF(A19="","",SUMIFS(Pointage[Prime Tâche (FCFA)],Pointage[ID Employé],A19,Pointage[Date],">="&$B$5,Pointage[Date],"<="&$D$5)) -> 0 | J19: =IF(OR(A19="",F19=""),0,ROUND(G19*F19,0)) -> 3312 | K19: =IF(OR(A19="",H19=""),0,ROUND(H19*'01_Employes'!N13,0)) -> 0 | L19: =IF(A19="","",J19+K19+I19) -> 3312 | M19: =IF(A19="","",COUNTIFS(Pointage[ID Employé],A19,Pointage[Date],">="&$B$5,Pointage[Date],"<="&$D$5,Pointage[Heures travaillées],">0")) -> 1
A20: =IF('01_Employes'!A14="","",'01_Employes'!A14) -> EMP009 | B20: =IF(A20="","",'01_Employes'!D14) -> Tineba Vital Eric | C20: =IF(A20="","",'01_Employes'!E14) -> Mécanicien | D20: =IF(A20="","",'01_Employes'!K14) -> Apprentissage | E20: =IF(A20="","",'01_Employes'!L14) -> 80000 | F20: =IF(A20="","",'01_Employes'!M14) -> 355 | G20: =IF(A20="","",SUMIFS(Pointage[Heures Normales],Pointage[ID Employé],A20,Pointage[Date],">="&$B$5,Pointage[Date],"<="&$D$5)) -> 8.75 | H20: =IF(A20="","",SUMIFS(Pointage[Heures Supp.],Pointage[ID Employé],A20,Pointage[Date],">="&$B$5,Pointage[Date],"<="&$D$5)) -> 0 | I20: =IF(A20="","",SUMIFS(Pointage[Prime Tâche (FCFA)],Pointage[ID Employé],A20,Pointage[Date],">="&$B$5,Pointage[Date],"<="&$D$5)) -> 0 | J20: =IF(OR(A20="",F20=""),0,ROUND(G20*F20,0)) -> 3106 | K20: =IF(OR(A20="",H20=""),0,ROUND(H20*'01_Employes'!N14,0)) -> 0 | L20: =IF(A20="","",J20+K20+I20) -> 3106 | M20: =IF(A20="","",COUNTIFS(Pointage[ID Employé],A20,Pointage[Date],">="&$B$5,Pointage[Date],"<="&$D$5,Pointage[Heures travaillées],">0")) -> 1
A21: =IF('01_Employes'!A15="","",'01_Employes'!A15) -> EMP010 | B21: =IF(A21="","",'01_Employes'!D15) -> Deutchoua Tientcheu Christian | C21: =IF(A21="","",'01_Employes'!E15) -> Mécanicien | D21: =IF(A21="","",'01_Employes'!K15) -> Apprentissage | E21: =IF(A21="","",'01_Employes'!L15) -> 80000 | F21: =IF(A21="","",'01_Employes'!M15) -> 355 | G21: =IF(A21="","",SUMIFS(Pointage[Heures Normales],Pointage[ID Employé],A21,Pointage[Date],">="&$B$5,Pointage[Date],"<="&$D$5)) -> 5 | H21: =IF(A21="","",SUMIFS(Pointage[Heures Supp.],Pointage[ID Employé],A21,Pointage[Date],">="&$B$5,Pointage[Date],"<="&$D$5)) -> 0 | I21: =IF(A21="","",SUMIFS(Pointage[Prime Tâche (FCFA)],Pointage[ID Employé],A21,Pointage[Date],">="&$B$5,Pointage[Date],"<="&$D$5)) -> 0 | J21: =IF(OR(A21="",F21=""),0,ROUND(G21*F21,0)) -> 1775 | K21: =IF(OR(A21="",H21=""),0,ROUND(H21*'01_Employes'!N15,0)) -> 0 | L21: =IF(A21="","",J21+K21+I21) -> 1775 | M21: =IF(A21="","",COUNTIFS(Pointage[ID Employé],A21,Pointage[Date],">="&$B$5,Pointage[Date],"<="&$D$5,Pointage[Heures travaillées],">0")) -> 1
A22: =IF('01_Employes'!A16="","",'01_Employes'!A16) -> EMP011 | B22: =IF(A22="","",'01_Employes'!D16) -> Fouakouet Youssoufa | C22: =IF(A22="","",'01_Employes'!E16) -> Électronicien | D22: =IF(A22="","",'01_Employes'!K16) -> Apprentissage | E22: =IF(A22="","",'01_Employes'!L16) -> 80000 | F22: =IF(A22="","",'01_Employes'!M16) -> 355 | G22: =IF(A22="","",SUMIFS(Pointage[Heures Normales],Pointage[ID Employé],A22,Pointage[Date],">="&$B$5,Pointage[Date],"<="&$D$5)) -> 7 | H22: =IF(A22="","",SUMIFS(Pointage[Heures Supp.],Pointage[ID Employé],A22,Pointage[Date],">="&$B$5,Pointage[Date],"<="&$D$5)) -> 0 | I22: =IF(A22="","",SUMIFS(Pointage[Prime Tâche (FCFA)],Pointage[ID Employé],A22,Pointage[Date],">="&$B$5,Pointage[Date],"<="&$D$5)) -> 0 | J22: =IF(OR(A22="",F22=""),0,ROUND(G22*F22,0)) -> 2485 | K22: =IF(OR(A22="",H22=""),0,ROUND(H22*'01_Employes'!N16,0)) -> 0 | L22: =IF(A22="","",J22+K22+I22) -> 2485 | M22: =IF(A22="","",COUNTIFS(Pointage[ID Employé],A22,Pointage[Date],">="&$B$5,Pointage[Date],"<="&$D$5,Pointage[Heures travaillées],">0")) -> 1
A23: =IF('01_Employes'!A17="","",'01_Employes'!A17) -> EMP012 | B23: =IF(A23="","",'01_Employes'!D17) -> Ngouamera Adrien Gildas | C23: =IF(A23="","",'01_Employes'!E17) -> Mécanicien | D23: =IF(A23="","",'01_Employes'!K17) -> Apprentissage | E23: =IF(A23="","",'01_Employes'!L17) -> 80000 | F23: =IF(A23="","",'01_Employes'!M17) -> 355 | G23: =IF(A23="","",SUMIFS(Pointage[Heures Normales],Pointage[ID Employé],A23,Pointage[Date],">="&$B$5,Pointage[Date],"<="&$D$5)) -> 8.93 | H23: =IF(A23="","",SUMIFS(Pointage[Heures Supp.],Pointage[ID Employé],A23,Pointage[Date],">="&$B$5,Pointage[Date],"<="&$D$5)) -> 0 | I23: =IF(A23="","",SUMIFS(Pointage[Prime Tâche (FCFA)],Pointage[ID Employé],A23,Pointage[Date],">="&$B$5,Pointage[Date],"<="&$D$5)) -> 0 | J23: =IF(OR(A23="",F23=""),0,ROUND(G23*F23,0)) -> 3170 | K23: =IF(OR(A23="",H23=""),0,ROUND(H23*'01_Employes'!N17,0)) -> 0 | L23: =IF(A23="","",J23+K23+I23) -> 3170 | M23: =IF(A23="","",COUNTIFS(Pointage[ID Employé],A23,Pointage[Date],">="&$B$5,Pointage[Date],"<="&$D$5,Pointage[Heures travaillées],">0")) -> 1
... A25: =IF('01_Employes'!A19="","",'01_Employes'!A19) -> EMP014 | B25: =IF(A25="","",'01_Employes'!D19) -> Zo'o Mbarga Jean Loic | C25: =IF(A25="","",'01_Employes'!E19) -> Mécanicien | D25: =IF(A25="","",'01_Employes'!K19) -> Apprentissage | E25: =IF(A25="","",'01_Employes'!L19) -> 80000 | F25: =IF(A25="","",'01_Employes'!M19) -> 355 | G25: =IF(A25="","",SUMIFS(Pointage[Heures Normales],Pointage[ID Employé],A25,Pointage[Date],">="&$B$5,Pointage[Date],"<="&$D$5)) -> 9 | H25: =IF(A25="","",SUMIFS(Pointage[Heures Supp.],Pointage[ID Employé],A25,Pointage[Date],">="&$B$5,Pointage[Date],"<="&$D$5)) -> 0 | I25: =IF(A25="","",SUMIFS(Pointage[Prime Tâche (FCFA)],Pointage[ID Employé],A25,Pointage[Date],">="&$B$5,Pointage[Date],"<="&$D$5)) -> 0 | J25: =IF(OR(A25="",F25=""),0,ROUND(G25*F25,0)) -> 3195 | K25: =IF(OR(A25="",H25=""),0,ROUND(H25*'01_Employes'!N19,0)) -> 0 | L25: =IF(A25="","",J25+K25+I25) -> 3195 | M25: =IF(A25="","",COUNTIFS(Pointage[ID Employé],A25,Pointage[Date],">="&$B$5,Pointage[Date],"<="&$D$5,Pointage[Heures travaillées],">0")) -> 1
G26: =SUM(G12:G25) -> 164.12 | H26: =SUM(H12:H25) -> 1 | I26: =SUM(I12:I25) -> 7500 | J26: =SUM(J12:J25) -> 78267 | K26: =SUM(K12:K25) -> 666 | L26: =SUM(L12:L25) -> 86433 | M26: =SUM(M12:M25) -> 21
A27: TOTAUX | G27: =SUM(G12:G25) -> 164.12 | H27: =SUM(H12:H25) -> 1 | I27: =SUM(I12:I25) -> 7500 | J27: =SUM(J12:J25) -> 78267 | K27: =SUM(K12:K25) -> 666 | L27: =SUM(L12:L25) -> 86433 | M27: =SUM(M12:M25) -> 21
A28: 1. Ce calcul est une ESTIMATION basée sur les heures pointées et les primes saisies. La paie officielle doit être validée par un expert-comptable.
A29: 2. Le salaire est calculé uniquement sur les heures réellement travaillées + primes de tâche + heures supplémentaires.
A30: 3. Si un employé a un salaire fixe mensuel indépendant des heures, vous pouvez ajuster manuellement dans la colonne Observations ou créer une règle spécifique.
A31: 4. Pour ajouter un nouvel employé : ajoutez-le d'abord dans 01_Employes, il apparaîtra automatiquement ici (étendez les formules si besoin).
A32: 5. Les primes de tâche peuvent être saisies jour par jour dans 02_Pointage ou regroupées sur une seule ligne avec la date souhaitée.

Sheet 04_Conges
A1: GESTION DES CONGÉS ET ABSENCES
A2: Enregistrez les demandes. Les soldes sont calculés automatiquement (droit annuel - jours pris).
A4: N° | B4: ID Employé | C4: Nom Complet | D4: Type d'absence | E4: Date début | F4: Date fin | G4: Nb jours | H4: Motif | I4: Statut demande | J4: Validé par | K4: Date validation | L4: Commentaire RH
A5: 1 | C5: =IF(B5="","",IFERROR(VLOOKUP(B5,Employes[[ID]:[Nom Complet]],4,FALSE()),"")) | G5: =IF(OR(E5="",F5=""),"",F5-E5+1)
A6: 2 | C6: =IF(B6="","",IFERROR(VLOOKUP(B6,Employes[[ID]:[Nom Complet]],4,FALSE()),"")) | G6: =IF(OR(E6="",F6=""),"",F6-E6+1)
A7: 3 | C7: =IF(B7="","",IFERROR(VLOOKUP(B7,Employes[[ID]:[Nom Complet]],4,FALSE()),"")) | G7: =IF(OR(E7="",F7=""),"",F7-E7+1)
A8: 4 | C8: =IF(B8="","",IFERROR(VLOOKUP(B8,Employes[[ID]:[Nom Complet]],4,FALSE()),"")) | G8: =IF(OR(E8="",F8=""),"",F8-E8+1)
A9: 5 | C9: =IF(B9="","",IFERROR(VLOOKUP(B9,Employes[[ID]:[Nom Complet]],4,FALSE()),"")) | G9: =IF(OR(E9="",F9=""),"",F9-E9+1)
A10: 6 | C10: =IF(B10="","",IFERROR(VLOOKUP(B10,Employes[[ID]:[Nom Complet]],4,FALSE()),"")) | G10: =IF(OR(E10="",F10=""),"",F10-E10+1)
A11: 7 | C11: =IF(B11="","",IFERROR(VLOOKUP(B11,Employes[[ID]:[Nom Complet]],4,FALSE()),"")) | G11: =IF(OR(E11="",F11=""),"",F11-E11+1)
A12: 8 | C12: =IF(B12="","",IFERROR(VLOOKUP(B12,Employes[[ID]:[Nom Complet]],4,FALSE()),"")) | G12: =IF(OR(E12="",F12=""),"",F12-E12+1)
A13: 9 | C13: =IF(B13="","",IFERROR(VLOOKUP(B13,Employes[[ID]:[Nom Complet]],4,FALSE()),"")) | G13: =IF(OR(E13="",F13=""),"",F13-E13+1)
A14: 10 | C14: =IF(B14="","",IFERROR(VLOOKUP(B14,Employes[[ID]:[Nom Complet]],4,FALSE()),"")) | G14: =IF(OR(E14="",F14=""),"",F14-E14+1)
A15: 11 | C15: =IF(B15="","",IFERROR(VLOOKUP(B15,Employes[[ID]:[Nom Complet]],4,FALSE()),"")) | G15: =IF(OR(E15="",F15=""),"",F15-E15+1)
A16: 12 | C16: =IF(B16="","",IFERROR(VLOOKUP(B16,Employes[[ID]:[Nom Complet]],4,FALSE()),"")) | G16: =IF(OR(E16="",F16=""),"",F16-E16+1)
... A24: 20 | C24: =IF(B24="","",IFERROR(VLOOKUP(B24,Employes[[ID]:[Nom Complet]],4,FALSE()),"")) | G24: =IF(OR(E24="",F24=""),"",F24-E24+1)
A27: SOLDES DE CONGÉS (calculés automatiquement)
A28: ID | B28: Nom Complet | C28: Droit annuel (jours) | D28: Jours pris (approuvés) | E28: Solde restant | F28: Notes
A29: =IF('01_Employes'!A6="","",'01_Employes'!A6) -> EMP001 | B29: =IF(A29="","",'01_Employes'!D6) -> Tsafack Ndongmo Symphonien | C29: 30 | D29: =IF(A29="","",SUMIFS($G$5:$G$24,$B$5:$B$24,A29,$I$5:$I$24,"Approuvé")) -> 0 | E29: =IF(A29="","",C29-D29) -> 30
A30: =IF('01_Employes'!A7="","",'01_Employes'!A7) -> EMP002 | B30: =IF(A30="","",'01_Employes'!D7) -> Pandja Tchatchoua Syriane | C30: 30 | D30: =IF(A30="","",SUMIFS($G$5:$G$24,$B$5:$B$24,A30,$I$5:$I$24,"Approuvé")) -> 0 | E30: =IF(A30="","",C30-D30) -> 30
A31: =IF('01_Employes'!A8="","",'01_Employes'!A8) -> EMP003 | B31: =IF(A31="","",'01_Employes'!D8) -> Takoueta Yvan | C31: 30 | D31: =IF(A31="","",SUMIFS($G$5:$G$24,$B$5:$B$24,A31,$I$5:$I$24,"Approuvé")) -> 0 | E31: =IF(A31="","",C31-D31) -> 30
A32: =IF('01_Employes'!A9="","",'01_Employes'!A9) -> EMP004 | B32: =IF(A32="","",'01_Employes'!D9) -> Chekep Faustin | C32: 30 | D32: =IF(A32="","",SUMIFS($G$5:$G$24,$B$5:$B$24,A32,$I$5:$I$24,"Approuvé")) -> 0 | E32: =IF(A32="","",C32-D32) -> 30
A33: =IF('01_Employes'!A10="","",'01_Employes'!A10) -> EMP005 | B33: =IF(A33="","",'01_Employes'!D10) -> Abdou | C33: 30 | D33: =IF(A33="","",SUMIFS($G$5:$G$24,$B$5:$B$24,A33,$I$5:$I$24,"Approuvé")) -> 0 | E33: =IF(A33="","",C33-D33) -> 30
A34: =IF('01_Employes'!A11="","",'01_Employes'!A11) -> EMP006 | B34: =IF(A34="","",'01_Employes'!D11) -> Nyontyen Si Jean Vinny | C34: 30 | D34: =IF(A34="","",SUMIFS($G$5:$G$24,$B$5:$B$24,A34,$I$5:$I$24,"Approuvé")) -> 0 | E34: =IF(A34="","",C34-D34) -> 30
A35: =IF('01_Employes'!A12="","",'01_Employes'!A12) -> EMP007 | B35: =IF(A35="","",'01_Employes'!D12) -> Holé Homsala | C35: 30 | D35: =IF(A35="","",SUMIFS($G$5:$G$24,$B$5:$B$24,A35,$I$5:$I$24,"Approuvé")) -> 0 | E35: =IF(A35="","",C35-D35) -> 30
A36: =IF('01_Employes'!A13="","",'01_Employes'!A13) -> EMP008 | B36: =IF(A36="","",'01_Employes'!D13) -> Ebene Ngono | C36: 30 | D36: =IF(A36="","",SUMIFS($G$5:$G$24,$B$5:$B$24,A36,$I$5:$I$24,"Approuvé")) -> 0 | E36: =IF(A36="","",C36-D36) -> 30
A37: =IF('01_Employes'!A14="","",'01_Employes'!A14) -> EMP009 | B37: =IF(A37="","",'01_Employes'!D14) -> Tineba Vital Eric | C37: 30 | D37: =IF(A37="","",SUMIFS($G$5:$G$24,$B$5:$B$24,A37,$I$5:$I$24,"Approuvé")) -> 0 | E37: =IF(A37="","",C37-D37) -> 30
A38: =IF('01_Employes'!A15="","",'01_Employes'!A15) -> EMP010 | B38: =IF(A38="","",'01_Employes'!D15) -> Deutchoua Tientcheu Christian | C38: 30 | D38: =IF(A38="","",SUMIFS($G$5:$G$24,$B$5:$B$24,A38,$I$5:$I$24,"Approuvé")) -> 0 | E38: =IF(A38="","",C38-D38) -> 30
A39: =IF('01_Employes'!A16="","",'01_Employes'!A16) -> EMP011 | B39: =IF(A39="","",'01_Employes'!D16) -> Fouakouet Youssoufa | C39: 30 | D39: =IF(A39="","",SUMIFS($G$5:$G$24,$B$5:$B$24,A39,$I$5:$I$24,"Approuvé")) -> 0 | E39: =IF(A39="","",C39-D39) -> 30
A40: =IF('01_Employes'!A17="","",'01_Employes'!A17) -> EMP012 | B40: =IF(A40="","",'01_Employes'!D17) -> Ngouamera Adrien Gildas | C40: 30 | D40: =IF(A40="","",SUMIFS($G$5:$G$24,$B$5:$B$24,A40,$I$5:$I$24,"Approuvé")) -> 0 | E40: =IF(A40="","",C40-D40) -> 30
A41: =IF('01_Employes'!A18="","",'01_Employes'!A18) -> EMP013 | B41: =IF(A41="","",'01_Employes'!D18) -> Nague Zemdjui Arnaud | C41: 30 | D41: =IF(A41="","",SUMIFS($G$5:$G$24,$B$5:$B$24,A41,$I$5:$I$24,"Approuvé")) -> 0 | E41: =IF(A41="","",C41-D41) -> 30

Sheet 05_Contrats
A1: SUIVI DES CONTRATS DE TRAVAIL
A3: ID | B3: Nom Complet | C3: Type contrat | D3: Date début | E3: Date fin | F3: Durée (mois) | G3: Fin période essai | H3: Salaire brut (FCFA) | I3: Avantages | J3: Renouvellement | K3: Observations
A4: =IF('01_Employes'!A6="","",'01_Employes'!A6) -> EMP001 | B4: =IF(A4="","",'01_Employes'!D6) -> Tsafack Ndongmo Symphonien | C4: =IF(A4="","",'01_Employes'!K6) -> CDI | F4: =IF(OR(D4="",E4=""),"",ROUND((E4-D4)/30,1)) | H4: =IF(A4="","",'01_Employes'!L6) -> 150000
A5: =IF('01_Employes'!A7="","",'01_Employes'!A7) -> EMP002 | B5: =IF(A5="","",'01_Employes'!D7) -> Pandja Tchatchoua Syriane | C5: =IF(A5="","",'01_Employes'!K7) -> CDI | F5: =IF(OR(D5="",E5=""),"",ROUND((E5-D5)/30,1)) | H5: =IF(A5="","",'01_Employes'!L7) -> 100000
A6: =IF('01_Employes'!A8="","",'01_Employes'!A8) -> EMP003 | B6: =IF(A6="","",'01_Employes'!D8) -> Takoueta Yvan | C6: =IF(A6="","",'01_Employes'!K8) -> CDI | F6: =IF(OR(D6="",E6=""),"",ROUND((E6-D6)/30,1)) | H6: =IF(A6="","",'01_Employes'!L8) -> 150000
A7: =IF('01_Employes'!A9="","",'01_Employes'!A9) -> EMP004 | B7: =IF(A7="","",'01_Employes'!D9) -> Chekep Faustin | C7: =IF(A7="","",'01_Employes'!K9) -> CDI | F7: =IF(OR(D7="",E7=""),"",ROUND((E7-D7)/30,1)) | H7: =IF(A7="","",'01_Employes'!L9) -> 120000
A8: =IF('01_Employes'!A10="","",'01_Employes'!A10) -> EMP005 | B8: =IF(A8="","",'01_Employes'!D10) -> Abdou | C8: =IF(A8="","",'01_Employes'!K10) -> Apprentissage | F8: =IF(OR(D8="",E8=""),"",ROUND((E8-D8)/30,1)) | H8: =IF(A8="","",'01_Employes'!L10) -> 80000
A9: =IF('01_Employes'!A11="","",'01_Employes'!A11) -> EMP006 | B9: =IF(A9="","",'01_Employes'!D11) -> Nyontyen Si Jean Vinny | C9: =IF(A9="","",'01_Employes'!K11) -> Apprentissage | F9: =IF(OR(D9="",E9=""),"",ROUND((E9-D9)/30,1)) | H9: =IF(A9="","",'01_Employes'!L11) -> 80000
A10: =IF('01_Employes'!A12="","",'01_Employes'!A12) -> EMP007 | B10: =IF(A10="","",'01_Employes'!D12) -> Holé Homsala | C10: =IF(A10="","",'01_Employes'!K12) -> Apprentissage | F10: =IF(OR(D10="",E10=""),"",ROUND((E10-D10)/30,1)) | H10: =IF(A10="","",'01_Employes'!L12) -> 80000
A11: =IF('01_Employes'!A13="","",'01_Employes'!A13) -> EMP008 | B11: =IF(A11="","",'01_Employes'!D13) -> Ebene Ngono | C11: =IF(A11="","",'01_Employes'!K13) -> Apprentissage | F11: =IF(OR(D11="",E11=""),"",ROUND((E11-D11)/30,1)) | H11: =IF(A11="","",'01_Employes'!L13) -> 80000
A12: =IF('01_Employes'!A14="","",'01_Employes'!A14) -> EMP009 | B12: =IF(A12="","",'01_Employes'!D14) -> Tineba Vital Eric | C12: =IF(A12="","",'01_Employes'!K14) -> Apprentissage | F12: =IF(OR(D12="",E12=""),"",ROUND((E12-D12)/30,1)) | H12: =IF(A12="","",'01_Employes'!L14) -> 80000
A13: =IF('01_Employes'!A15="","",'01_Employes'!A15) -> EMP010 | B13: =IF(A13="","",'01_Employes'!D15) -> Deutchoua Tientcheu Christian | C13: =IF(A13="","",'01_Employes'!K15) -> Apprentissage | F13: =IF(OR(D13="",E13=""),"",ROUND((E13-D13)/30,1)) | H13: =IF(A13="","",'01_Employes'!L15) -> 80000
A14: =IF('01_Employes'!A16="","",'01_Employes'!A16) -> EMP011 | B14: =IF(A14="","",'01_Employes'!D16) -> Fouakouet Youssoufa | C14: =IF(A14="","",'01_Employes'!K16) -> Apprentissage | F14: =IF(OR(D14="",E14=""),"",ROUND((E14-D14)/30,1)) | H14: =IF(A14="","",'01_Employes'!L16) -> 80000
A15: =IF('01_Employes'!A17="","",'01_Employes'!A17) -> EMP012 | B15: =IF(A15="","",'01_Employes'!D17) -> Ngouamera Adrien Gildas | C15: =IF(A15="","",'01_Employes'!K17) -> Apprentissage | F15: =IF(OR(D15="",E15=""),"",ROUND((E15-D15)/30,1)) | H15: =IF(A15="","",'01_Employes'!L17) -> 80000
A16: =IF('01_Employes'!A18="","",'01_Employes'!A18) -> EMP013 | B16: =IF(A16="","",'01_Employes'!D18) -> Nague Zemdjui Arnaud | C16: =IF(A16="","",'01_Employes'!K18) -> CDD | F16: =IF(OR(D16="",E16=""),"",ROUND((E16-D16)/30,1)) | H16: =IF(A16="","",'01_Employes'!L18) -> 200000

Sheet 06_Competences
A1: COMPÉTENCES, FORMATIONS & HABILITATIONS
A3: ID | B3: Nom Complet | C3: Poste | D3: Spécialité principale | E3: Niveau (1-5) | F3: Formations suivies | G3: Habilitations / Certifications | H3: Logiciels maîtrisés | I3: Langues | J3: Points forts | K3: Axes d'amélioration | L3: Dernière évaluation
A4: =IF('01_Employes'!A6="","",'01_Employes'!A6) -> EMP001 | B4: =IF(A4="","",'01_Employes'!D6) -> Tsafack Ndongmo Symphonien | C4: =IF(A4="","",'01_Employes'!E6) -> Administrateur
A5: =IF('01_Employes'!A7="","",'01_Employes'!A7) -> EMP002 | B5: =IF(A5="","",'01_Employes'!D7) -> Pandja Tchatchoua Syriane | C5: =IF(A5="","",'01_Employes'!E7) -> Secrétaire
A6: =IF('01_Employes'!A8="","",'01_Employes'!A8) -> EMP003 | B6: =IF(A6="","",'01_Employes'!D8) -> Takoueta Yvan | C6: =IF(A6="","",'01_Employes'!E8) -> Chef des ateliers
A7: =IF('01_Employes'!A9="","",'01_Employes'!A9) -> EMP004 | B7: =IF(A7="","",'01_Employes'!D9) -> Chekep Faustin | C7: =IF(A7="","",'01_Employes'!E9) -> Mécanicien
A8: =IF('01_Employes'!A10="","",'01_Employes'!A10) -> EMP005 | B8: =IF(A8="","",'01_Employes'!D10) -> Abdou | C8: =IF(A8="","",'01_Employes'!E10) -> Tôlier
A9: =IF('01_Employes'!A11="","",'01_Employes'!A11) -> EMP006 | B9: =IF(A9="","",'01_Employes'!D11) -> Nyontyen Si Jean Vinny | C9: =IF(A9="","",'01_Employes'!E11) -> Mécanicien
A10: =IF('01_Employes'!A12="","",'01_Employes'!A12) -> EMP007 | B10: =IF(A10="","",'01_Employes'!D12) -> Holé Homsala | C10: =IF(A10="","",'01_Employes'!E12) -> Magasinier
A11: =IF('01_Employes'!A13="","",'01_Employes'!A13) -> EMP008 | B11: =IF(A11="","",'01_Employes'!D13) -> Ebene Ngono | C11: =IF(A11="","",'01_Employes'!E13) -> Mécanicien
A12: =IF('01_Employes'!A14="","",'01_Employes'!A14) -> EMP009 | B12: =IF(A12="","",'01_Employes'!D14) -> Tineba Vital Eric | C12: =IF(A12="","",'01_Employes'!E14) -> Mécanicien
A13: =IF('01_Employes'!A15="","",'01_Employes'!A15) -> EMP010 | B13: =IF(A13="","",'01_Employes'!D15) -> Deutchoua Tientcheu Christian | C13: =IF(A13="","",'01_Employes'!E15) -> Mécanicien
A14: =IF('01_Employes'!A16="","",'01_Employes'!A16) -> EMP011 | B14: =IF(A14="","",'01_Employes'!D16) -> Fouakouet Youssoufa | C14: =IF(A14="","",'01_Employes'!E16) -> Électronicien
A15: =IF('01_Employes'!A17="","",'01_Employes'!A17) -> EMP012 | B15: =IF(A15="","",'01_Employes'!D17) -> Ngouamera Adrien Gildas | C15: =IF(A15="","",'01_Employes'!E17) -> Mécanicien
A16: =IF('01_Employes'!A18="","",'01_Employes'!A18) -> EMP013 | B16: =IF(A16="","",'01_Employes'!D18) -> Nague Zemdjui Arnaud | C16: =IF(A16="","",'01_Employes'!E18) -> Assistant Administratif

Sheet 07_Planning
A1: PLANNING HEBDOMADAIRE / AFFECTATIONS
A2: Semaine du : | B2: 46251 | C2: au | D2: 46256
A4: ID | B4: Nom Complet | C4: Poste | D4: Lundi | E4: Mardi | F4: Mercredi | G4: Jeudi | H4: Vendredi | I4: Samedi
A5: =IF('01_Employes'!A6="","",'01_Employes'!A6) -> EMP001 | B5: =IF(A5="","",'01_Employes'!D6) -> Tsafack Ndongmo Symphonien | C5: =IF(A5="","",'01_Employes'!E6) -> Administrateur
A6: =IF('01_Employes'!A7="","",'01_Employes'!A7) -> EMP002 | B6: =IF(A6="","",'01_Employes'!D7) -> Pandja Tchatchoua Syriane | C6: =IF(A6="","",'01_Employes'!E7) -> Secrétaire
A7: =IF('01_Employes'!A8="","",'01_Employes'!A8) -> EMP003 | B7: =IF(A7="","",'01_Employes'!D8) -> Takoueta Yvan | C7: =IF(A7="","",'01_Employes'!E8) -> Chef des ateliers
A8: =IF('01_Employes'!A9="","",'01_Employes'!A9) -> EMP004 | B8: =IF(A8="","",'01_Employes'!D9) -> Chekep Faustin | C8: =IF(A8="","",'01_Employes'!E9) -> Mécanicien
A9: =IF('01_Employes'!A10="","",'01_Employes'!A10) -> EMP005 | B9: =IF(A9="","",'01_Employes'!D10) -> Abdou | C9: =IF(A9="","",'01_Employes'!E10) -> Tôlier
A10: =IF('01_Employes'!A11="","",'01_Employes'!A11) -> EMP006 | B10: =IF(A10="","",'01_Employes'!D11) -> Nyontyen Si Jean Vinny | C10: =IF(A10="","",'01_Employes'!E11) -> Mécanicien
A11: =IF('01_Employes'!A12="","",'01_Employes'!A12) -> EMP007 | B11: =IF(A11="","",'01_Employes'!D12) -> Holé Homsala | C11: =IF(A11="","",'01_Employes'!E12) -> Magasinier
A12: =IF('01_Employes'!A13="","",'01_Employes'!A13) -> EMP008 | B12: =IF(A12="","",'01_Employes'!D13) -> Ebene Ngono | C12: =IF(A12="","",'01_Employes'!E13) -> Mécanicien
A13: =IF('01_Employes'!A14="","",'01_Employes'!A14) -> EMP009 | B13: =IF(A13="","",'01_Employes'!D14) -> Tineba Vital Eric | C13: =IF(A13="","",'01_Employes'!E14) -> Mécanicien
A14: =IF('01_Employes'!A15="","",'01_Employes'!A15) -> EMP010 | B14: =IF(A14="","",'01_Employes'!D15) -> Deutchoua Tientcheu Christian | C14: =IF(A14="","",'01_Employes'!E15) -> Mécanicien
A15: =IF('01_Employes'!A16="","",'01_Employes'!A16) -> EMP011 | B15: =IF(A15="","",'01_Employes'!D16) -> Fouakouet Youssoufa | C15: =IF(A15="","",'01_Employes'!E16) -> Électronicien
A16: =IF('01_Employes'!A17="","",'01_Employes'!A17) -> EMP012 | B16: =IF(A16="","",'01_Employes'!D17) -> Ngouamera Adrien Gildas | C16: =IF(A16="","",'01_Employes'!E17) -> Mécanicien
A17: =IF('01_Employes'!A18="","",'01_Employes'!A18) -> EMP013 | B17: =IF(A17="","",'01_Employes'!D18) -> Nague Zemdjui Arnaud | C17: =IF(A17="","",'01_Employes'!E18) -> Assistant Administratif
A19: Exemples d'affectation : Atelier – Pont 1 | Magasin | Accueil | Congé | Formation | Extérieur | Carrosserie | Diagnostic...

Sheet 08_Sanctions
A1: REGISTRE DES INCIDENTS, AVERTISSEMENTS & SANCTIONS
A3: N° | B3: Date | C3: ID Employé | D3: Nom Complet | E3: Type | F3: Description des faits | G3: Gravité | H3: Décision / Sanction | I3: Notifié le | J3: Observations
A4: 1 | D4: =IF(C4="","",IFERROR(VLOOKUP(C4,Employes[[ID]:[Nom Complet]],4,FALSE()),""))
A5: 2 | D5: =IF(C5="","",IFERROR(VLOOKUP(C5,Employes[[ID]:[Nom Complet]],4,FALSE()),""))
A6: 3 | D6: =IF(C6="","",IFERROR(VLOOKUP(C6,Employes[[ID]:[Nom Complet]],4,FALSE()),""))
A7: 4 | D7: =IF(C7="","",IFERROR(VLOOKUP(C7,Employes[[ID]:[Nom Complet]],4,FALSE()),""))
A8: 5 | D8: =IF(C8="","",IFERROR(VLOOKUP(C8,Employes[[ID]:[Nom Complet]],4,FALSE()),""))
A9: 6 | D9: =IF(C9="","",IFERROR(VLOOKUP(C9,Employes[[ID]:[Nom Complet]],4,FALSE()),""))
A10: 7 | D10: =IF(C10="","",IFERROR(VLOOKUP(C10,Employes[[ID]:[Nom Complet]],4,FALSE()),""))
A11: 8 | D11: =IF(C11="","",IFERROR(VLOOKUP(C11,Employes[[ID]:[Nom Complet]],4,FALSE()),""))
A12: 9 | D12: =IF(C12="","",IFERROR(VLOOKUP(C12,Employes[[ID]:[Nom Complet]],4,FALSE()),""))
A13: 10 | D13: =IF(C13="","",IFERROR(VLOOKUP(C13,Employes[[ID]:[Nom Complet]],4,FALSE()),""))
A14: 11 | D14: =IF(C14="","",IFERROR(VLOOKUP(C14,Employes[[ID]:[Nom Complet]],4,FALSE()),""))
A15: 12 | D15: =IF(C15="","",IFERROR(VLOOKUP(C15,Employes[[ID]:[Nom Complet]],4,FALSE()),""))
... A19: 16 | D19: =IF(C19="","",IFERROR(VLOOKUP(C19,Employes[[ID]:[Nom Complet]],4,FALSE()),""))

Sheet 09_Contacts
A1: ANNUAIRE INTERNE — CONTACTS RAPIDES
A3: ID | B3: Nom Complet | C3: Poste | D3: Téléphone | E3: Email | F3: Département
A4: =IF('01_Employes'!A6="","",'01_Employes'!A6) -> EMP001 | B4: =IF(A4="","",'01_Employes'!D6) -> Tsafack Ndongmo Symphonien | C4: =IF(A4="","",'01_Employes'!E6) -> Administrateur | D4: =IF(A4="","",'01_Employes'!G6) -> 677 89 71 62 | E4: =IF(A4="","",'01_Employes'!H6) -> 0 | F4: =IF(A4="","",'01_Employes'!F6) -> Administration
A5: =IF('01_Employes'!A7="","",'01_Employes'!A7) -> EMP002 | B5: =IF(A5="","",'01_Employes'!D7) -> Pandja Tchatchoua Syriane | C5: =IF(A5="","",'01_Employes'!E7) -> Secrétaire | D5: =IF(A5="","",'01_Employes'!G7) -> 656 04 71 31 | E5: =IF(A5="","",'01_Employes'!H7) -> 0 | F5: =IF(A5="","",'01_Employes'!F7) -> Administration
A6: =IF('01_Employes'!A8="","",'01_Employes'!A8) -> EMP003 | B6: =IF(A6="","",'01_Employes'!D8) -> Takoueta Yvan | C6: =IF(A6="","",'01_Employes'!E8) -> Chef des ateliers | D6: =IF(A6="","",'01_Employes'!G8) -> 657 78 99 78 | E6: =IF(A6="","",'01_Employes'!H8) -> 0 | F6: =IF(A6="","",'01_Employes'!F8) -> Direction Atelier
A7: =IF('01_Employes'!A9="","",'01_Employes'!A9) -> EMP004 | B7: =IF(A7="","",'01_Employes'!D9) -> Chekep Faustin | C7: =IF(A7="","",'01_Employes'!E9) -> Mécanicien | D7: =IF(A7="","",'01_Employes'!G9) -> 672 67 18 01 | E7: =IF(A7="","",'01_Employes'!H9) -> 0 | F7: =IF(A7="","",'01_Employes'!F9) -> Atelier Mécanique
A8: =IF('01_Employes'!A10="","",'01_Employes'!A10) -> EMP005 | B8: =IF(A8="","",'01_Employes'!D10) -> Abdou | C8: =IF(A8="","",'01_Employes'!E10) -> Tôlier | D8: =IF(A8="","",'01_Employes'!G10) -> 673 84 48 12 | E8: =IF(A8="","",'01_Employes'!H10) -> 0 | F8: =IF(A8="","",'01_Employes'!F10) -> Carrosserie
A9: =IF('01_Employes'!A11="","",'01_Employes'!A11) -> EMP006 | B9: =IF(A9="","",'01_Employes'!D11) -> Nyontyen Si Jean Vinny | C9: =IF(A9="","",'01_Employes'!E11) -> Mécanicien | D9: =IF(A9="","",'01_Employes'!G11) -> 694 36 28 38 | E9: =IF(A9="","",'01_Employes'!H11) -> 0 | F9: =IF(A9="","",'01_Employes'!F11) -> Atelier Mécanique
A10: =IF('01_Employes'!A12="","",'01_Employes'!A12) -> EMP007 | B10: =IF(A10="","",'01_Employes'!D12) -> Holé Homsala | C10: =IF(A10="","",'01_Employes'!E12) -> Magasinier | D10: =IF(A10="","",'01_Employes'!G12) -> 699 47 09 80 | E10: =IF(A10="","",'01_Employes'!H12) -> holehomsala7@gmail.com | F10: =IF(A10="","",'01_Employes'!F12) -> Magasin
A11: =IF('01_Employes'!A13="","",'01_Employes'!A13) -> EMP008 | B11: =IF(A11="","",'01_Employes'!D13) -> Ebene Ngono | C11: =IF(A11="","",'01_Employes'!E13) -> Mécanicien | D11: =IF(A11="","",'01_Employes'!G13) -> 653 04 86 11 | E11: =IF(A11="","",'01_Employes'!H13) -> 0 | F11: =IF(A11="","",'01_Employes'!F13) -> Atelier Mécanique
A12: =IF('01_Employes'!A14="","",'01_Employes'!A14) -> EMP009 | B12: =IF(A12="","",'01_Employes'!D14) -> Tineba Vital Eric | C12: =IF(A12="","",'01_Employes'!E14) -> Mécanicien | D12: =IF(A12="","",'01_Employes'!G14) -> 698 14 24 06 | E12: =IF(A12="","",'01_Employes'!H14) -> 0 | F12: =IF(A12="","",'01_Employes'!F14) -> Atelier Mécanique
A13: =IF('01_Employes'!A15="","",'01_Employes'!A15) -> EMP010 | B13: =IF(A13="","",'01_Employes'!D15) -> Deutchoua Tientcheu Christian | C13: =IF(A13="","",'01_Employes'!E15) -> Mécanicien | D13: =IF(A13="","",'01_Employes'!G15) -> 695 07 89 78 / 678 03 61 47 | E13: =IF(A13="","",'01_Employes'!H15) -> 0 | F13: =IF(A13="","",'01_Employes'!F15) -> Atelier Mécanique
A14: =IF('01_Employes'!A16="","",'01_Employes'!A16) -> EMP011 | B14: =IF(A14="","",'01_Employes'!D16) -> Fouakouet Youssoufa | C14: =IF(A14="","",'01_Employes'!E16) -> Électronicien | D14: =IF(A14="","",'01_Employes'!G16) -> 640 85 90 53 / 620 04 32 29 | E14: =IF(A14="","",'01_Employes'!H16) -> 0 | F14: =IF(A14="","",'01_Employes'!F16) -> Atelier Mécanique
A15: =IF('01_Employes'!A17="","",'01_Employes'!A17) -> EMP012 | B15: =IF(A15="","",'01_Employes'!D17) -> Ngouamera Adrien Gildas | C15: =IF(A15="","",'01_Employes'!E17) -> Mécanicien | D15: =IF(A15="","",'01_Employes'!G17) -> 680 09 48 64 | E15: =IF(A15="","",'01_Employes'!H17) -> 0 | F15: =IF(A15="","",'01_Employes'!F17) -> Atelier Mécanique
... A17: =IF('01_Employes'!A19="","",'01_Employes'!A19) -> EMP014 | B17: =IF(A17="","",'01_Employes'!D19) -> Zo'o Mbarga Jean Loic | C17: =IF(A17="","",'01_Employes'!E19) -> Mécanicien | D17: =IF(A17="","",'01_Employes'!G19) -> 698 94 92 21 | E17: =IF(A17="","",'01_Employes'!H19) -> 0 | F17: =IF(A17="","",'01_Employes'!F19) -> Atelier Mécanique

Sheet 10_Mode_Emploi
A1: MODE D'EMPLOI — GESTION DU PERSONNEL PRO
A3: OBJECTIF
A4: Ce classeur professionnel permet de gérer l'ensemble du personnel du Garage Polyvalent Junior avec automatisation complète des calculs de présence, heures et paie.
A6: MODULE | B6: UTILISATION
A7: 00_Parametres | B7: Paramètres globaux : heures standard/jour, majoration HS, listes de référence. Modifiez les cellules jaunes selon vos besoins.
A8: 01_Employes | B8: SOURCE DE VÉRITÉ. Fiche de chaque collaborateur. Complétez les cases jaunes (date d'embauche, salaire de base, CNPS, adresse...). Les taux horaires se calculent automatiquement.
A9: 02_Pointage | B9: Saisissez chaque jour (ou en batch) : Date + ID Employé + Heure Arrivée + Heure Départ + Code Présence + Prime de Tâche éventuelle. Les heures normales et HS se calculent automatiquement.
A10: 03_Paie | B10: Le cœur du système. Choisissez une période (dates début/fin). Le salaire de chaque employé est calculé automatiquement : (Heures Normales × Taux Horaire) + (HS × Taux HS) + Primes de Tâche.
A11: 04_Conges | B11: Enregistrez les demandes de congés/absences. Les soldes se mettent à jour automatiquement quand le statut = Approuvé.
A12: 05_Contrats | B12: Suivi des types de contrats, dates et renouvellements. Lié aux données employés.
A13: 06_Competences | B13: Cartographie des compétences, formations et axes d'amélioration.
A14: 07_Planning | B14: Planning hebdomadaire d'affectation des équipes.
A15: 08_Sanctions | B15: Registre disciplinaire et incidents.
A16: 09_Contacts | B16: Annuaire interne 100% automatique (lié à 01_Employes).
A18: RÈGLES D'OR
A19: 1. Ne modifiez JAMAIS les formules (cellules VERTES).
A20: 2. Remplissez uniquement les cellules JAUNES (saisie).
A21: 3. Ajoutez un nouvel employé en bas de la feuille 01_Employes (respectez le format ID : EMP014, EMP015...). Les formules des autres feuilles s'étendront si vous copiez les lignes.
A22: 4. Pour la présence : une ligne = un employé + un jour. Saisissez les heures au format HH:MM.
A23: 5. Les primes de tâche se saisissent dans 02_Pointage (colonne K). Vous pouvez en mettre plusieurs par jour ou regrouper.
A24: 6. Sauvegardez une copie du fichier chaque mois (ex: Paie_Aout_2026.xlsx).
A25: 7. La paie calculée est une ESTIMATION. Faites toujours valider par un expert-comptable avant paiement.
A27: LOGIQUE DE CALCUL DU SALAIRE
A28: Taux Horaire = Salaire Base Mensuel ÷ Heures Standard Mensuelles (paramétrable dans 00_Parametres)
A29: Heures Normales = MIN(Heures travaillées du jour, Seuil HS)
A30: Heures Supplémentaires = MAX(0, Heures travaillées - Seuil HS)
... A33: Salaire Brut Estimé = Montant Normal + Montant HS + Σ Primes de Tâche de la période
